{"file":"hero_xubai04.png","frames":{"i_130":{"h":72,"y":474,"x":601,"w":114},"i_238":{"h":94,"y":173,"x":1863,"w":104},"i_119":{"h":49,"y":98,"x":365,"w":48},"i_198":{"h":39,"y":19,"x":173,"w":38},"i_200":{"h":39,"y":19,"x":133,"w":38},"i_232":{"h":278,"y":1259,"x":1027,"w":190},"i_115":{"h":72,"y":496,"x":401,"w":60},"i_163":{"h":46,"y":166,"x":809,"w":80},"i_224":{"h":221,"y":1707,"x":0,"w":195},"i_301":{"h":113,"y":986,"x":928,"w":279},"i_109":{"h":54,"y":44,"x":1077,"w":64},"i_167":{"h":78,"y":223,"x":1488,"w":114},"i_300":{"h":113,"y":873,"x":1262,"w":279},"i_247":{"h":46,"y":303,"x":1229,"w":300},"i_231":{"h":278,"y":1710,"x":1501,"w":182},"i_259":{"h":52,"y":289,"x":0,"w":46},"i_14":{"h":56,"y":286,"x":297,"w":51},"i_307":{"h":65,"y":406,"x":759,"w":126},"i_225":{"h":222,"y":1015,"x":722,"w":181},"i_203":{"h":45,"y":47,"x":54,"w":37},"i_160":{"h":54,"y":0,"x":1794,"w":87},"i_211":{"h":51,"y":47,"x":93,"w":34},"i_114":{"h":91,"y":565,"x":1246,"w":168},"i_213":{"h":34,"y":0,"x":0,"w":23},"i_65":{"h":90,"y":218,"x":1057,"w":83},"i_86":{"h":56,"y":154,"x":743,"w":64},"i_25":{"h":58,"y":623,"x":121,"w":78},"i_302":{"h":91,"y":780,"x":1416,"w":270},"i_201":{"h":41,"y":0,"x":224,"w":35},"i_18":{"h":54,"y":150,"x":473,"w":49},"i_248":{"h":53,"y":17,"x":1516,"w":104},"i_85":{"h":65,"y":594,"x":0,"w":53},"i_278":{"h":43,"y":51,"x":466,"w":56},"i_158":{"h":68,"y":153,"x":891,"w":58},"i_16":{"h":48,"y":0,"x":647,"w":52},"i_71":{"h":44,"y":291,"x":127,"w":63},"i_181":{"h":147,"y":583,"x":1106,"w":109},"i_261":{"h":17,"y":0,"x":159,"w":63},"i_61":{"h":44,"y":94,"x":42,"w":45},"i_267":{"h":55,"y":48,"x":818,"w":61},"i_223":{"h":250,"y":1458,"x":653,"w":185},"i_2":{"h":56,"y":236,"x":247,"w":48},"i_78":{"h":55,"y":161,"x":1114,"w":92},"i_69":{"h":53,"y":292,"x":350,"w":55},"i_24":{"h":55,"y":50,"x":524,"w":46},"i_129":{"h":72,"y":549,"x":128,"w":46},"i_112":{"h":84,"y":472,"x":1659,"w":170},"i_262":{"h":35,"y":10,"x":90,"w":41},"i_228":{"h":50,"y":483,"x":0,"w":63},"i_230":{"h":280,"y":975,"x":1543,"w":190},"i_166":{"h":75,"y":162,"x":1655,"w":114},"i_280":{"h":41,"y":12,"x":327,"w":50},"i_142":{"h":80,"y":233,"x":581,"w":38},"i_153":{"h":49,"y":549,"x":59,"w":67},"i_111":{"h":61,"y":513,"x":244,"w":53},"i_141":{"h":80,"y":414,"x":401,"w":54},"i_226":{"h":292,"y":988,"x":1735,"w":189},"i_89":{"h":57,"y":152,"x":621,"w":52},"i_11":{"h":43,"y":191,"x":311,"w":62},"i_174":{"h":149,"y":473,"x":742,"w":91},"i_266":{"h":55,"y":600,"x":59,"w":60},"i_303":{"h":66,"y":654,"x":1752,"w":280},"i_37":{"h":12,"y":177,"x":235,"w":195},"i_178":{"h":157,"y":806,"x":591,"w":115},"i_59":{"h":44,"y":374,"x":464,"w":93},"i_268":{"h":56,"y":356,"x":407,"w":55},"i_57":{"h":51,"y":195,"x":39,"w":44},"i_62":{"h":49,"y":50,"x":632,"w":53},"i_53":{"h":53,"y":174,"x":1208,"w":131},"i_75":{"h":67,"y":54,"x":952,"w":53},"i_90":{"h":56,"y":103,"x":1186,"w":70},"i_76":{"h":56,"y":96,"x":572,"w":47},"i_241":{"h":156,"y":1101,"x":928,"w":211},"i_107":{"h":59,"y":326,"x":579,"w":69},"i_204":{"h":49,"y":0,"x":439,"w":41},"i_250":{"h":56,"y":0,"x":1226,"w":63},"i_106":{"h":141,"y":755,"x":287,"w":136},"i_220":{"h":217,"y":1239,"x":722,"w":187},"i_55":{"h":42,"y":294,"x":213,"w":69},"i_236":{"h":266,"y":1754,"x":364,"w":160},"i_240":{"h":156,"y":966,"x":250,"w":229},"i_291":{"h":12,"y":418,"x":0,"w":253},"i_29":{"h":60,"y":188,"x":1341,"w":145},"i_293":{"h":82,"y":576,"x":234,"w":54},"i_249":{"h":221,"y":1456,"x":1219,"w":331},"i_184":{"h":93,"y":275,"x":1721,"w":121},"i_229":{"h":224,"y":1710,"x":1066,"w":220},"i_265":{"h":55,"y":317,"x":467,"w":55},"i_270":{"h":202,"y":1544,"x":393,"w":219},"i_77":{"h":57,"y":323,"x":692,"w":71},"i_222":{"h":250,"y":1710,"x":698,"w":186},"i_221":{"h":223,"y":1529,"x":206,"w":185},"i_56":{"h":46,"y":46,"x":254,"w":46},"i_12":{"h":44,"y":245,"x":143,"w":62},"i_175":{"h":139,"y":284,"x":1142,"w":85},"i_205":{"h":52,"y":12,"x":379,"w":41},"i_84":{"h":59,"y":291,"x":525,"w":52},"i_165":{"h":79,"y":239,"x":1604,"w":115},"i_26":{"h":37,"y":134,"x":1772,"w":196},"i_51":{"h":59,"y":162,"x":1513,"w":140},"i_176":{"h":153,"y":651,"x":591,"w":116},"i_52":{"h":63,"y":504,"x":463,"w":136},"i_82":{"h":101,"y":72,"x":1973,"w":52},"i_177":{"h":157,"y":680,"x":429,"w":122},"i_91":{"h":51,"y":100,"x":881,"w":69},"i_243":{"h":80,"y":320,"x":1531,"w":175},"i_271":{"h":221,"y":988,"x":1209,"w":253},"i_19":{"h":45,"y":139,"x":138,"w":50},"i_294":{"h":82,"y":420,"x":464,"w":52},"i_286":{"h":67,"y":585,"x":1752,"w":270},"i_10":{"h":46,"y":0,"x":818,"w":61},"i_108":{"h":66,"y":544,"x":307,"w":66},"i_93":{"h":53,"y":432,"x":120,"w":60},"i_32":{"h":50,"y":0,"x":1007,"w":68},"i_209":{"h":53,"y":43,"x":213,"w":39},"i_30":{"h":43,"y":338,"x":213,"w":70},"i_139":{"h":32,"y":154,"x":524,"w":83},"i_164":{"h":44,"y":372,"x":112,"w":69},"i_50":{"h":59,"y":413,"x":601,"w":139},"i_264":{"h":47,"y":139,"x":89,"w":47},"i_70":{"h":72,"y":238,"x":938,"w":104},"i_269":{"h":200,"y":1124,"x":241,"w":204},"i_288":{"h":32,"y":250,"x":1142,"w":279},"i_118":{"h":109,"y":762,"x":738,"w":157},"i_173":{"h":139,"y":372,"x":1922,"w":85},"i_246":{"h":65,"y":516,"x":1011,"w":233},"i_41":{"h":101,"y":269,"x":1863,"w":109},"i_116":{"h":102,"y":701,"x":897,"w":170},"i_63":{"h":52,"y":0,"x":941,"w":64},"i_285":{"h":102,"y":732,"x":1069,"w":243},"i_218":{"h":49,"y":101,"x":621,"w":60},"i_169":{"h":100,"y":173,"x":1771,"w":90},"i_187":{"h":40,"y":60,"x":129,"w":54},"i_298":{"h":58,"y":535,"x":176,"w":56},"i_168":{"h":76,"y":100,"x":1064,"w":48},"i_170":{"h":100,"y":370,"x":1721,"w":114},"i_287":{"h":66,"y":898,"x":287,"w":291},"i_309":{"h":56,"y":103,"x":1114,"w":70},"i_143":{"h":54,"y":0,"x":1160,"w":64},"i_67":{"h":53,"y":458,"x":244,"w":61},"i_258":{"h":32,"y":12,"x":261,"w":64},"i_251":{"h":57,"y":0,"x":881,"w":58},"i_138":{"h":45,"y":56,"x":1143,"w":81},"i_208":{"h":53,"y":140,"x":39,"w":42},"i_186":{"h":49,"y":432,"x":0,"w":63},"i_49":{"h":101,"y":548,"x":601,"w":135},"i_124":{"h":161,"y":983,"x":0,"w":239},"i_199":{"h":35,"y":10,"x":54,"w":34},"i_155":{"h":70,"y":0,"x":1977,"w":69},"i_217":{"h":52,"y":96,"x":473,"w":49},"i_274":{"h":243,"y":1211,"x":1219,"w":296},"i_252":{"h":48,"y":236,"x":297,"w":56},"i_110":{"h":53,"y":432,"x":182,"w":60},"i_151":{"h":53,"y":183,"x":951,"w":104},"i_263":{"h":41,"y":55,"x":321,"w":52},"i_306":{"h":56,"y":233,"x":525,"w":54},"i_40":{"h":42,"y":107,"x":683,"w":71},"i_7":{"h":43,"y":191,"x":247,"w":62},"i_60":{"h":54,"y":0,"x":1705,"w":87},"i_73":{"h":55,"y":54,"x":1883,"w":88},"i_210":{"h":54,"y":99,"x":0,"w":37},"i_128":{"h":54,"y":51,"x":687,"w":54},"i_296":{"h":56,"y":214,"x":806,"w":71},"i_22":{"h":49,"y":0,"x":701,"w":51},"i_245":{"h":45,"y":152,"x":675,"w":66},"i_123":{"h":161,"y":1178,"x":481,"w":239},"i_126":{"h":58,"y":0,"x":1370,"w":67},"i_27":{"h":70,"y":513,"x":1831,"w":207},"i_42":{"h":106,"y":409,"x":887,"w":122},"i_179":{"h":160,"y":821,"x":0,"w":123},"i_161":{"h":42,"y":0,"x":1077,"w":81},"i_183":{"h":95,"y":312,"x":938,"w":83},"i_150":{"h":53,"y":56,"x":1622,"w":106},"i_39":{"h":43,"y":132,"x":260,"w":50},"i_47":{"h":116,"y":583,"x":969,"w":135},"i_21":{"h":60,"y":487,"x":120,"w":54},"i_104":{"h":58,"y":52,"x":1291,"w":67},"i_152":{"h":49,"y":241,"x":355,"w":56},"i_9":{"h":45,"y":0,"x":754,"w":62},"i_157":{"h":57,"y":535,"x":0,"w":57},"i_113":{"h":80,"y":462,"x":307,"w":54},"i_68":{"h":72,"y":343,"x":0,"w":46},"i_260":{"h":42,"y":188,"x":85,"w":55},"i_28":{"h":71,"y":748,"x":83,"w":202},"i_305":{"h":10,"y":0,"x":261,"w":176},"i_125":{"h":58,"y":123,"x":952,"w":63},"i_284":{"h":131,"y":842,"x":1688,"w":218},"i_36":{"h":26,"y":134,"x":1513,"w":257},"i_239":{"h":126,"y":634,"x":738,"w":132},"i_102":{"h":54,"y":261,"x":467,"w":56},"i_171":{"h":139,"y":310,"x":1044,"w":91},"i_149":{"h":67,"y":337,"x":765,"w":100},"i_122":{"h":161,"y":1015,"x":481,"w":239},"i_117":{"h":63,"y":52,"x":1007,"w":55},"i_172":{"h":139,"y":372,"x":1837,"w":83},"i_13":{"h":45,"y":371,"x":48,"w":62},"i_66":{"h":66,"y":199,"x":676,"w":55},"i_180":{"h":160,"y":821,"x":125,"w":123},"i_279":{"h":43,"y":0,"x":482,"w":56},"i_103":{"h":46,"y":98,"x":213,"w":45},"i_234":{"h":266,"y":1710,"x":886,"w":178},"i_188":{"h":44,"y":50,"x":572,"w":58},"i_253":{"h":53,"y":403,"x":285,"w":57},"i_43":{"h":109,"y":569,"x":463,"w":126},"i_45":{"h":113,"y":351,"x":1229,"w":129},"i_281":{"h":113,"y":223,"x":879,"w":57},"i_8":{"h":44,"y":276,"x":63,"w":62},"i_282":{"h":148,"y":836,"x":1069,"w":191},"i_254":{"h":47,"y":322,"x":48,"w":59},"i_295":{"h":55,"y":269,"x":621,"w":69},"i_121":{"h":161,"y":1341,"x":0,"w":239},"i_17":{"h":53,"y":206,"x":473,"w":50},"i_212":{"h":42,"y":10,"x":25,"w":27},"i_289":{"h":21,"y":111,"x":1516,"w":270},"i_38":{"h":8,"y":0,"x":25,"w":132},"i_58":{"h":63,"y":272,"x":806,"w":64},"i_227":{"h":250,"y":1458,"x":840,"w":185},"i_4":{"h":56,"y":404,"x":344,"w":55},"i_290":{"h":15,"y":0,"x":1439,"w":264},"i_237":{"h":266,"y":1754,"x":206,"w":156},"i_44":{"h":112,"y":402,"x":1531,"w":126},"i_79":{"h":201,"y":1326,"x":241,"w":204},"i_20":{"h":59,"y":432,"x":65,"w":53},"i_92":{"h":52,"y":212,"x":733,"w":71},"i_120":{"h":161,"y":1178,"x":0,"w":239},"i_275":{"h":234,"y":1710,"x":1288,"w":211},"i_277":{"h":43,"y":117,"x":415,"w":56},"i_154":{"h":55,"y":299,"x":407,"w":56},"i_46":{"h":115,"y":517,"x":835,"w":132},"i_48":{"h":102,"y":651,"x":290,"w":137},"i_162":{"h":33,"y":337,"x":127,"w":84},"i_156":{"h":49,"y":66,"x":415,"w":49},"i_87":{"h":57,"y":129,"x":1344,"w":103},"i_159":{"h":63,"y":683,"x":121,"w":72},"i_31":{"h":43,"y":188,"x":525,"w":70},"i_23":{"h":42,"y":232,"x":85,"w":56},"i_257":{"h":35,"y":102,"x":129,"w":62},"i_88":{"h":101,"y":84,"x":1449,"w":62},"i_207":{"h":53,"y":146,"x":190,"w":43},"i_80":{"h":201,"y":1504,"x":0,"w":204},"i_292":{"h":82,"y":657,"x":55,"w":57},"i_6":{"h":46,"y":47,"x":754,"w":62},"i_219":{"h":48,"y":0,"x":540,"w":51},"i_283":{"h":164,"y":614,"x":1416,"w":149},"i_33":{"h":50,"y":0,"x":1291,"w":77},"i_81":{"h":201,"y":1341,"x":447,"w":204},"i_299":{"h":42,"y":201,"x":190,"w":55},"i_3":{"h":56,"y":211,"x":621,"w":53},"i_244":{"h":48,"y":191,"x":375,"w":56},"i_74":{"h":69,"y":56,"x":1788,"w":93},"i_182":{"h":138,"y":425,"x":1360,"w":106},"i_185":{"h":65,"y":17,"x":1439,"w":75},"i_255":{"h":36,"y":94,"x":260,"w":59},"i_276":{"h":48,"y":0,"x":593,"w":52},"i_235":{"h":268,"y":1748,"x":526,"w":170},"i_140":{"h":59,"y":105,"x":818,"w":60},"i_64":{"h":58,"y":741,"x":0,"w":81},"i_134":{"h":228,"y":1456,"x":1552,"w":325},"i_105":{"h":67,"y":60,"x":1360,"w":74},"i_34":{"h":118,"y":722,"x":1688,"w":240},"i_54":{"h":52,"y":0,"x":1883,"w":92},"i_35":{"h":54,"y":558,"x":1468,"w":282},"i_15":{"h":55,"y":266,"x":733,"w":69},"i_127":{"h":55,"y":347,"x":350,"w":53},"i_202":{"h":43,"y":54,"x":0,"w":40},"i_242":{"h":140,"y":873,"x":708,"w":218},"i_308":{"h":56,"y":420,"x":524,"w":75},"i_297":{"h":57,"y":95,"x":756,"w":60},"i_206":{"h":51,"y":98,"x":321,"w":42},"i_72":{"h":57,"y":344,"x":285,"w":53},"i_5":{"h":56,"y":241,"x":413,"w":52},"i_233":{"h":276,"y":1710,"x":1685,"w":186},"i_256":{"h":39,"y":248,"x":0,"w":61},"i_304":{"h":24,"y":387,"x":559,"w":198},"i_83":{"h":60,"y":112,"x":1258,"w":84}}}
