{"file":"assist_ichigo_white200.png","frames":{"i_18":{"h":152,"y":0,"x":516,"w":276},"i_7":{"h":50,"y":0,"x":48,"w":53},"i_14":{"h":54,"y":296,"x":0,"w":64},"i_1":{"h":56,"y":0,"x":103,"w":49},"i_20":{"h":54,"y":267,"x":66,"w":107},"i_6":{"h":44,"y":110,"x":0,"w":68},"i_12":{"h":18,"y":0,"x":0,"w":46},"i_4":{"h":49,"y":156,"x":40,"w":64},"i_11":{"h":80,"y":109,"x":106,"w":54},"i_15":{"h":68,"y":191,"x":133,"w":100},"i_10":{"h":58,"y":207,"x":57,"w":74},"i_8":{"h":58,"y":0,"x":154,"w":79},"i_17":{"h":108,"y":0,"x":794,"w":476},"i_2":{"h":56,"y":52,"x":0,"w":53},"i_21":{"h":54,"y":352,"x":0,"w":104},"i_5":{"h":49,"y":58,"x":55,"w":64},"i_19":{"h":120,"y":0,"x":1272,"w":452},"i_16":{"h":85,"y":60,"x":175,"w":339},"i_13":{"h":80,"y":156,"x":0,"w":38},"i_3":{"h":56,"y":238,"x":0,"w":55}}}
