{"fileName":"hero_mayuri","version":1596797684445,"sArr":["l_404","l_236","l_316","l_1","l_356","l_239","l_2","l_347","l_391","l_474","l_264","l_376","l_370","l_415","l_375","l_369","l_331","l_255","l_228","l_26","l_283","l_452","l_469","l_273","l_412","l_280","l_405","l_311","l_242","l_455"],"imgScale":{},"inputScale":1,"stageHgith":1,"scale":1,"clipping":{"clippingPadding":3},"imgP":{"i_101":{},"i_137":{},"i_140":{},"i_73":{},"i_75":{},"i_107":{},"i_10":{},"i_201":{},"i_151":{},"i_172":{},"i_74":{},"i_169":{},"i_191":{},"i_46":{},"i_70":{},"i_71":{},"i_204":{},"i_120":{},"i_133":{},"i_77":{},"i_117":{},"i_129":{},"i_138":{},"i_78":{},"i_199":{},"i_208":{},"i_76":{},"i_121":{},"i_207":{},"i_9":{},"i_83":{},"i_79":{},"i_51":{},"i_105":{},"i_164":{},"i_38":{},"i_128":{},"i_80":{},"i_12":{},"i_196":{},"i_22":{},"i_43":{},"i_85":{},"i_47":{},"i_163":{},"i_37":{},"i_122":{},"i_72":{},"i_82":{},"i_139":{},"i_173":{},"i_26":{},"i_178":{},"i_84":{},"i_209":{},"i_187":{},"i_13":{},"i_123":{},"i_57":{},"i_55":{},"i_143":{},"i_40":{},"i_124":{},"i_93":{},"i_8":{},"i_126":{},"i_147":{},"i_24":{},"i_95":{},"i_81":{},"i_54":{},"i_180":{},"i_32":{},"i_183":{},"i_25":{},"i_92":{},"i_127":{},"i_125":{},"i_182":{},"i_171":{},"i_145":{},"i_90":{},"i_44":{},"i_17":{},"i_34":{},"i_205":{},"i_16":{},"i_186":{},"i_135":{},"i_88":{},"i_170":{},"i_27":{},"i_165":{},"i_118":{},"i_146":{},"i_91":{},"i_176":{},"i_174":{},"i_162":{},"i_59":{},"i_132":{},"i_160":{},"i_175":{},"i_197":{},"i_195":{},"i_41":{},"i_158":{},"i_168":{},"i_96":{},"i_58":{},"i_108":{},"i_189":{},"i_192":{},"i_14":{},"i_39":{},"i_5":{},"i_53":{},"i_63":{},"i_115":{},"i_179":{},"i_198":{},"i_131":{},"i_155":{},"i_61":{},"i_15":{},"i_4":{},"i_60":{},"i_19":{},"i_97":{},"i_114":{},"i_161":{},"i_30":{},"i_188":{},"i_48":{},"i_64":{},"i_35":{},"i_62":{},"i_148":{},"i_185":{},"i_42":{},"i_33":{},"i_87":{},"i_152":{},"i_49":{},"i_11":{},"i_113":{},"i_203":{},"i_2":{},"i_94":{},"i_103":{},"i_65":{},"i_20":{},"i_153":{},"i_29":{},"i_184":{},"i_66":{},"i_181":{},"i_7":{},"i_149":{},"i_104":{},"i_112":{},"i_28":{},"i_6":{},"i_67":{},"i_200":{},"i_193":{},"i_156":{},"i_177":{},"i_98":{},"i_154":{},"i_100":{},"i_36":{},"i_89":{},"i_68":{},"i_111":{},"i_202":{},"i_119":{},"i_106":{},"i_56":{},"i_110":{},"i_31":{},"i_136":{},"i_134":{},"i_69":{},"i_166":{},"i_3":{},"i_99":{},"i_144":{},"i_18":{},"i_23":{},"i_109":{},"i_116":{},"i_194":{},"i_157":{},"i_159":{},"i_45":{},"i_86":{},"i_142":{},"i_150":{},"i_21":{},"i_130":{},"i_102":{},"i_50":{},"i_190":{},"i_141":{},"i_167":{},"i_52":{},"i_206":{}},"imgArr":[{"size":0,"name":"0"},{"size":0,"name":"1"}],"stageWidth":1,"mcObjs":{"mc_0":{"direction":1,"frameTime":33,"stageHeight":58,"layers":[[{"libName":"i_2","x":16.85,"y":-7.15,"frameNum":2},{"libName":"i_3","x":15.85,"y":-7.15,"frameNum":2},{"libName":"i_4","x":14.85,"y":-7.15,"frameNum":2}]],"screenH":640,"totalFrame":9},"root":{"direction":1,"frameTime":33,"stageHeight":1,"layers":[[{},{"libName":"mc","x":-0.65,"y":-23.9,"mcName":"mc"}]],"screenH":640,"totalFrame":2},"mc_3":{"direction":1,"frameTime":33,"stageHeight":48,"layers":[[{"libName":"i_15","x":50,"al":0.6,"y":34.5},{"x":41.1,"al":0.54,"y":26.8},{"x":32.2,"al":0.47,"y":19.05},{"x":23.35,"al":0.4,"y":11.35},{"x":14.45,"al":0.34,"y":3.6},{"x":5.55,"al":0.27,"y":-4.1},{"x":-3.35,"al":0.2,"y":-11.85},{"x":-12.2,"al":0.13,"y":-19.55},{"x":-21.1,"al":0.07,"y":-27.3},{"x":-30,"al":0,"y":-35},{"x":50,"al":0.6,"y":34.5},{"x":41.1,"al":0.54,"y":26.8},{"x":32.2,"al":0.47,"y":19.05},{"x":23.35,"al":0.41,"y":11.35},{"x":14.45,"al":0.34,"y":3.6}],[{"frameNum":3},{"libName":"i_15","x":50,"al":0.6,"y":34.5},{"x":41.1,"al":0.54,"y":26.8},{"x":32.2,"al":0.47,"y":19.05},{"x":23.35,"al":0.4,"y":11.35},{"x":14.45,"al":0.34,"y":3.6},{"x":5.55,"al":0.27,"y":-4.1},{"x":-3.35,"al":0.2,"y":-11.85},{"x":-12.2,"al":0.13,"y":-19.55},{"x":-21.1,"al":0.07,"y":-27.3},{"x":-30,"al":0,"y":-35},{"x":50,"al":0.6,"y":34.5}]],"screenH":640,"totalFrame":15},"zh2atm":{"direction":1,"stageHeight":20.5,"frameTime":33,"soundObj":{"16":[{"libName":"l_331"}]},"layers":[[{"libName":"i_55","x":-5.05,"y":-17},{"x":0.36,"b":0.4314,"y":-18.56,"c":-0.4314,"d":0.9008,"a":0.9008},{"x":6.11,"b":0.7803,"y":-17.66,"c":-0.7803,"d":0.6228,"a":0.6228},{"x":10.77,"b":0.9745,"y":-14.35,"c":-0.9745,"d":0.2212,"a":0.2212},{"x":13.62,"b":0.9745,"y":-9.34,"c":-0.9745,"d":-0.2212,"a":-0.2212},{"x":14.39,"b":0.7803,"y":-2.11,"c":-0.7803,"d":-0.6228,"a":-0.6228},{"x":11.32,"b":0.4314,"y":2.93,"c":-0.4314,"d":-0.9008,"a":-0.9008},{"x":8.35,"d":-1,"y":4.55,"a":-1},{"x":3.54,"b":-0.4314,"y":6.41,"c":0.4314,"d":-0.9008,"a":-0.9008},{"x":-3.01,"b":-0.7803,"y":6.26,"c":0.7803,"d":-0.6228,"a":-0.6228},{"x":-8.62,"b":-0.9745,"y":2.85,"c":0.9745,"d":-0.2212,"a":-0.2212},{"x":-11.37,"b":-0.9745,"y":-2.26,"c":0.9745,"d":0.2212,"a":0.2212},{"x":-11.14,"b":-0.7803,"y":-5.79,"c":0.7803,"d":0.6228,"a":0.6228},{"x":-9.32,"b":-0.4314,"y":-13.18,"c":0.4314,"d":0.9008,"a":0.9008},{"x":-5.05,"y":-17,"frameNum":1},{"x":63.45,"libName":"mc_5","y":-154.1,"blendMode":"add","d":0.6099,"a":-0.6099,"frameNum":26},{}]],"screenH":640,"frameLabels":{"loop":{"end":16,"begin":15},"hit":{"begin":16}},"totalFrame":44},"cbsmian":{"direction":1,"frameTime":33,"stageHeight":41.5,"layers":[[{"libName":"i_1","x":0,"y":0}],[{}]],"screenH":640,"frameLabels":{"pai":{"begin":0}},"totalFrame":1},"AImain":{"direction":1,"frameTime":33,"stageHeight":1,"layers":[[{},{"libName":"cbsmian","b":-0.0011,"y":-65.75,"c":0.0003,"x":-57.65,"d":2.2086,"a":6.5273,"mcName":"cbsmian"}],[{},{"libName":"cbsmian","b":-9.4236,"y":253.4,"c":30.8731,"x":-567.05,"d":-0.0048,"a":-0.0015,"mcName":"sbsmian"}],[{},{"libName":"cbsmian","b":-0.0003,"y":-22.85,"c":0.0001,"x":18.75,"d":0.8657,"a":1.7206,"mcName":"bsmian"}],[{},{"libName":"cbsmian","y":-110.85,"c":0,"x":101.25,"d":1.0428,"a":1.178,"mcName":"zh3mian"}],[{},{"libName":"cbsmian","y":-42.2,"x":7.3,"d":1.6255,"mcName":"zh2mian","a":3.9353}],[{},{"libName":"cbsmian","y":-42.8,"x":8.25,"d":1.6553,"mcName":"zh1mian","a":3.9324}],[{},{"libName":"cbsmian","y":-47.15,"x":9.15,"d":1.7437,"mcName":"kj2mian","a":1.3497}],[{},{"libName":"cbsmian","y":-27.05,"x":8.45,"d":0.5727,"mcName":"kj1mian","a":2.0973}],[{},{"libName":"cbsmian","y":-10.7,"x":-1.1,"d":0.8497,"mcName":"kanmian","a":0.8082}],[{},{"libName":"cbsmian","b":-0.6371,"y":29.6,"c":3.7164,"x":8.2,"d":3.7165,"a":0.637,"mcName":"tzmian"}],[{},{"libName":"cbsmian","y":-51.25,"x":16.35,"d":1.7043,"mcName":"tkanmian","a":1.5777}]],"screenH":640,"totalFrame":2},"mc_6":{"direction":1,"frameTime":33,"stageHeight":176,"layers":[[{"libName":"i_108","x":2,"y":3},{"libName":"i_109","x":6,"y":1},{"libName":"i_110","x":19,"y":4},{"libName":"i_111","x":4,"y":6},{"libName":"i_112","x":4,"y":6},{"libName":"i_113","x":1,"y":8},{"libName":"i_114","x":2,"y":9},{"libName":"i_115","x":1,"y":13},{"frameNum":6}]],"screenH":640,"frameLabels":{"stop":{"begin":8}},"totalFrame":15},"mc_5":{"direction":1,"frameTime":33,"stageHeight":276,"layers":[[{"libName":"i_56","x":44,"y":179},{"libName":"i_57","x":20,"y":138},{"libName":"i_58","x":13,"y":106},{"libName":"i_59","x":8,"y":84},{"libName":"i_60","x":5,"y":67},{"libName":"i_61","x":3,"y":54},{"libName":"i_62","x":2,"y":43},{"libName":"i_63","x":1,"y":34},{"libName":"i_64","x":1,"y":25},{"libName":"i_65","x":1,"y":17},{"libName":"i_66","x":2,"y":13},{"libName":"i_67","x":3,"y":8},{"libName":"i_68","x":4,"y":5},{"libName":"i_69","x":5,"y":3},{"libName":"i_70","x":6,"y":3},{"libName":"i_71","x":8,"y":1},{"libName":"i_72","x":11,"y":3},{"libName":"i_73","x":16,"y":4},{"libName":"i_74","x":15,"y":7},{"libName":"i_75","x":14,"y":9},{"libName":"i_76","x":13,"y":11},{"libName":"i_77","x":12,"y":14},{"libName":"i_78","x":11,"y":18},{"libName":"i_79","x":11,"y":21},{"libName":"i_80","x":10,"y":26},{"libName":"i_81","x":9,"y":32},{"libName":"i_82","x":13,"y":39},{"libName":"i_83","x":12,"y":48},{"libName":"i_84","x":30,"y":59},{"libName":"i_85","x":31,"y":75},{"libName":"i_86","x":29,"y":142},{"libName":"i_87","x":25,"y":153},{"libName":"i_88","x":24,"y":166},{"libName":"i_89","x":21,"y":207},{"libName":"i_90","x":21,"y":228},{"libName":"i_91","x":22,"y":239},{}]],"screenH":640,"totalFrame":37},"mc_2":{"direction":1,"frameTime":33,"stageHeight":45,"layers":[[{"libName":"i_10","x":27.1,"y":28.55,"frameNum":2}]],"screenH":640,"totalFrame":3},"mc_7":{"direction":1,"frameTime":33,"stageHeight":172,"layers":[[{"libName":"i_116","x":12,"y":8},{"libName":"i_117","x":12,"y":0},{"libName":"i_118","x":12,"y":1},{"libName":"i_119","x":12,"y":6},{"libName":"i_120","x":11,"y":11},{"libName":"i_121","x":11,"y":11},{"libName":"i_122","x":12,"y":12},{"libName":"i_123","x":12,"y":12},{"libName":"i_124","x":14,"y":13},{"libName":"i_125","x":12,"y":13},{"libName":"i_126","x":10,"y":13},{"libName":"i_127","x":2,"y":14},{"libName":"i_128","x":4,"y":17},{"libName":"i_129","x":6,"y":27},{"libName":"i_130","x":13,"y":35},{"libName":"i_131","x":18,"y":41},{"libName":"i_132","x":20,"y":55},{"libName":"i_133","x":24,"y":90},{"libName":"i_134","x":26,"y":120},{}]],"screenH":640,"frameLabels":{"stop":{"begin":19}},"totalFrame":20},"mc":{"direction":1,"stageHeight":622.7,"frameTime":33,"soundObj":{"440":[{"libName":"l_280"}],"194":[{"libName":"l_264"},{"libName":"l_236"}],"581":[{"libName":"l_369"}],"54":[{"libName":"l_228"}],"1160":[{"libName":"l_474"}],"201":[{"libName":"l_273"},{"libName":"l_255"}],"267":[{"libName":"l_239"}],"837":[{"libName":"l_452"}],"270":[{"libName":"l_242"}],"655":[{"libName":"l_255"}],"1104":[{"libName":"l_474"}],"401":[{"libName":"l_280"},{"libName":"l_228"}],"146":[{"libName":"l_236"}],"651":[{"libName":"l_391"}],"468":[{"libName":"l_239"}],"470":[{"libName":"l_242"}],"536":[{"libName":"l_316"}],"346":[{"libName":"l_311"},{"libName":"l_236"}],"91":[{"libName":"l_236"}],"604":[{"libName":"l_236"}],"671":[{"libName":"l_239"},{"libName":"l_242"}],"792":[{"libName":"l_415"}],"410":[{"libName":"l_347"}],"411":[{"libName":"l_255"}],"612":[{"libName":"l_375"},{"libName":"l_376"}],"168":[{"libName":"l_255"}],"874":[{"libName":"l_455"}],"235":[{"libName":"l_280"}],"603":[{"libName":"l_370"}],"237":[{"libName":"l_283"}],"110":[{"libName":"l_239"}],"500":[{"libName":"l_356"}],"685":[{"libName":"l_347"}],"302":[{"libName":"l_316"}],"1080":[{"libName":"l_469"}],"123":[{"libName":"l_242"}],"300":[{"libName":"l_311"}],"702":[{"libName":"l_404"},{"libName":"l_405"}],"750":[{"libName":"l_412"}]},"layers":[[{"frameNum":1216,"libName":"AImain","x":0.5,"y":0.45,"mcName":"AImain"}],[{"libName":"mc_0","x":-31,"y":-24.75,"frameNum":8},{"libName":"i_5","x":-13.8,"y":-32.85,"frameNum":1},{"libName":"i_6","x":-16.55,"y":-32.85,"frameNum":1},{"libName":"i_7","x":-16.55,"y":-31.85,"frameNum":1},{"libName":"i_8","x":-17.05,"y":-31.85,"frameNum":1},{"libName":"i_5","x":-14.05,"y":-33.1,"frameNum":1},{"libName":"i_6","x":-17.3,"y":-33.1,"frameNum":1},{"libName":"i_7","x":-18.05,"y":-31.85,"frameNum":1},{"libName":"i_8","x":-17.55,"y":-32.1,"frameNum":8},{"libName":"i_9","x":-28,"y":-23.45,"frameNum":9},{"libName":"mc_0","x":-31,"y":-24.75,"frameNum":9},{"libName":"i_10","x":-16.05,"y":-19.05,"frameNum":4},{"libName":"i_11","x":-15.05,"y":-37.05,"frameNum":4},{"libName":"i_12","x":-19.3,"y":-35.6,"frameNum":9},{"libName":"mc_2","x":-43.65,"y":-46.7,"frameNum":16},{"libName":"i_12","x":-19.3,"y":-35.6,"frameNum":1},{"libName":"i_13","x":-16.9,"y":-36.15,"frameNum":2},{"libName":"i_14","x":-16.4,"y":-26.6,"frameNum":13},{"libName":"mc_3","x":-80.3,"y":-69,"frameNum":11},{"libName":"i_15","x":-30.65,"y":-34.95,"frameNum":2},{"libName":"i_16","x":-28.8,"y":-30.25,"frameNum":1},{"libName":"i_17","x":-30.3,"y":-29.75,"frameNum":1},{"libName":"i_18","x":-29.3,"y":-30.95,"frameNum":16},{"libName":"i_2","x":-14.15,"y":-31.9},{"libName":"i_19","x":-19.15,"y":-32.4,"frameNum":1},{"libName":"i_20","x":-15.8,"y":-32.55,"frameNum":8},{"libName":"mc_0","x":-31,"y":-24.75,"frameNum":8},{"libName":"i_21","x":-17.95,"y":-40.5,"frameNum":2},{"libName":"i_22","x":-18.95,"y":-33.5,"frameNum":2},{"libName":"i_23","x":-18.95,"y":-33,"frameNum":13},{"x":-18.8,"y":-33.3,"frameNum":15},{"libName":"i_29","x":-14.65,"y":-31.1,"frameNum":30},{"libName":"i_33","y":-33.24,"x":-15.86,"d":0.95,"a":0.95,"frameNum":3},{"libName":"i_34","y":-32.29,"x":-15.86,"d":0.95,"a":0.95,"frameNum":1},{"libName":"i_35","y":-32.29,"x":-15.86,"d":0.95,"a":0.95,"frameNum":1},{"libName":"i_36","y":-32.29,"x":-15.86,"d":0.95,"a":0.95,"frameNum":1},{"libName":"i_37","y":-32.29,"x":-15.86,"d":0.95,"a":0.95,"frameNum":3},{"libName":"i_36","y":-32.29,"x":-15.86,"d":0.95,"a":0.95,"frameNum":1},{"libName":"i_38","y":-32.29,"x":-15.86,"d":0.95,"a":0.95,"frameNum":1},{"libName":"i_39","y":-32.3,"x":-15.98,"d":0.95,"a":0.95,"frameNum":15},{"libName":"i_40","x":-24.3,"al":0.5,"y":-20.3,"frameNum":1},{"libName":"i_41","x":-21.3,"al":0.5,"y":-35.1},{"x":-21.3,"y":-35.1},{"libName":"i_42","x":-30.8,"y":-46.55,"frameNum":1},{"libName":"i_43","x":-31.8,"y":-46.6,"frameNum":1},{"libName":"i_44","x":-31.3,"y":-47.05,"frameNum":22},{"libName":"i_45","x":-18.5,"y":-32.25,"frameNum":2},{"libName":"i_39","x":-18.5,"y":-34.05,"frameNum":37},{"libName":"i_45","x":-17.6,"y":-32.65,"frameNum":7},{"libName":"i_39","x":-17.6,"y":-34.45,"frameNum":49},{"libName":"i_92","x":-17.3,"y":-32.6,"frameNum":3},{"libName":"i_33","y":-33.04,"x":-4.71,"d":0.95,"a":0.95,"frameNum":20},{"libName":"i_29","x":-14.65,"y":-31.1,"frameNum":13},{"libName":"i_39","x":-17.6,"y":-34.45,"frameNum":4},{"libName":"i_33","y":-33.04,"x":-14.71,"d":0.95,"a":0.95,"frameNum":20},{"libName":"i_29","x":-24.65,"y":-31.1,"frameNum":1},{"libName":"i_39","x":-17.6,"y":-34.45,"frameNum":4},{"libName":"i_40","x":-24.3,"y":-20.3,"frameNum":1},{"libName":"i_41","x":-21.3,"y":-35.1,"frameNum":1},{"libName":"i_42","x":-30.8,"y":-46.55,"frameNum":1},{"libName":"i_43","x":-31.8,"y":-46.6,"frameNum":1},{"libName":"i_44","x":-31.3,"y":-47.05,"frameNum":18},{"libName":"i_92","x":-17.55,"y":-32.75,"frameNum":1},{"libName":"i_101","x":-17.55,"y":-35.75,"frameNum":1},{"libName":"i_102","x":-17.55,"y":-35.75,"frameNum":25},{"libName":"i_103","x":-17.55,"y":-35.75,"frameNum":1},{"libName":"i_104","x":-17.55,"y":-35.75,"frameNum":1},{"frameNum":1},{"libName":"i_105","x":-16.05,"y":-26.75,"frameNum":1},{"libName":"i_106","x":-16.05,"y":-26.75,"frameNum":1},{"libName":"i_107","x":-16.05,"y":-26.75,"frameNum":1},{"libName":"i_135","x":-16.05,"y":-26.75,"frameNum":41},{"libName":"i_29","x":-14.8,"y":-31.15,"frameNum":23},{"libName":"i_39","x":-17.3,"y":-35.7,"frameNum":22},{"libName":"i_29","x":-14.8,"y":-31.15,"frameNum":21},{"libName":"i_144","x":-17,"y":-33.7,"frameNum":21},{"libName":"i_40","x":-27,"y":-20.45,"frameNum":1},{"libName":"i_41","x":-24,"y":-35.25,"frameNum":1},{"libName":"i_42","x":-33.5,"y":-46.7,"frameNum":1},{"libName":"i_43","x":-34.5,"y":-46.75,"frameNum":1},{"libName":"i_44","x":-34,"y":-47.2,"frameNum":23},{"libName":"i_13","x":-18.05,"y":-32.3,"frameNum":2},{"libName":"i_14","x":-17.55,"y":-22.75,"frameNum":38},{"libName":"i_144","x":-17.5,"y":-32.85,"frameNum":1},{"libName":"i_101","x":-17.3,"y":-35.6,"frameNum":1},{"libName":"i_102","x":-17.3,"y":-35.6,"frameNum":1},{"libName":"i_151","x":-17.3,"y":-35.6,"frameNum":62},{"libName":"i_158","x":58.6,"y":-53.95,"frameNum":1},{"libName":"i_159","x":49.6,"y":-120.95,"frameNum":1},{"libName":"i_160","x":46.6,"y":-164.95,"frameNum":1},{"libName":"i_161","x":39.6,"y":-183.95,"frameNum":1},{},{"libName":"i_163","x":-258.9,"y":-126.6,"frameNum":51},{"frameNum":3,"libName":"wk","x":119.25,"y":24.7,"mcName":"wk"},{"frameNum":85},{"libName":"i_144","x":-17.5,"y":-32.85,"frameNum":26},{"libName":"i_45","x":-20.4,"y":-34.4,"frameNum":1},{"libName":"i_200","x":-20.1,"y":-37.4,"frameNum":3},{"libName":"i_45","x":-20.4,"y":-34.4,"frameNum":11},{"libName":"i_201","x":-17.15,"y":-34.6,"frameNum":2},{"libName":"i_202","x":-16.15,"y":-35.6,"frameNum":9},{"libName":"i_203","x":-29.65,"y":-16.45,"frameNum":4},{"libName":"i_204","x":-34.15,"y":3.75,"frameNum":9},{"libName":"i_205","x":-35.25,"y":-23.15,"frameNum":8},{"libName":"i_204","x":-34.15,"y":3.75,"frameNum":8},{"libName":"i_206","x":-15.45,"y":-19.35,"frameNum":21},{"libName":"i_45","x":-17.5,"y":-33.95,"frameNum":22},{"libName":"i_207","y":-36.25,"x":-17.44,"d":0.95,"a":0.95,"frameNum":1},{"libName":"i_208","y":-37.3,"x":-17.14,"d":0.95,"a":0.95,"frameNum":36},{"libName":"i_207","y":-36.25,"x":-17.44,"d":0.95,"a":0.95,"frameNum":1},{"libName":"i_209","y":-36.35,"x":-17.03,"d":0.95,"a":0.95,"frameNum":15},{"libName":"i_207","y":-36.5,"x":-17.14,"d":0.95,"a":0.95,"frameNum":1},{"libName":"i_208","y":-37.45,"x":-17.09,"d":0.95,"a":0.95,"frameNum":27},{"libName":"i_201","x":-17.35,"y":-34.35,"frameNum":29}],[{"frameNum":90},{"libName":"cbsmian","y":-36.25,"frameNum":2,"x":-6.35,"d":1.4631,"mcName":"tkatm","a":0.7726},{"frameNum":13},{"libName":"i_15","x":-30.65,"y":-34.95,"frameNum":11},{"libName":"cbsmian","y":-39.25,"frameNum":1,"x":-24.7,"d":1.413,"mcName":"tz1atm","a":0.8848},{"frameNum":1},{"libName":"cbsmian","y":-34.25,"frameNum":2,"x":6.3,"d":1.413,"mcName":"tzatm","a":0.8848},{"frameNum":17},{"libName":"cbsmian","y":-11.3,"frameNum":1,"x":-1.3,"d":0.844,"mcName":"k1atm","a":0.5012},{"frameNum":20},{"libName":"cbsmian","y":-23.3,"frameNum":1,"x":-15.4,"d":0.4889,"mcName":"k2atm","a":0.6427},{"frameNum":15},{"libName":"i_24","x":29,"y":-30.5,"frameNum":1},{"libName":"i_25","x":28.25,"y":-18.65,"frameNum":5},{"libName":"i_26","x":32.75,"y":-19.8},{"x":35.85,"y":-19.8},{"libName":"i_27","x":37.65,"y":-20.35},{"x":38.25,"y":-20.35,"frameNum":2},{"libName":"i_28","x":35.6,"y":-16.95},{"libName":"i_30","x":41.1,"y":-15.2},{"x":47.5,"y":-15.2},{"x":53.9,"y":-15.2},{"libName":"i_31","x":57.9,"y":-15.2},{"x":60.3,"y":-15.2},{"x":61.1,"y":-15.2,"frameNum":6},{"libName":"i_32","x":61.1,"y":-15.25,"frameNum":1},{"libName":"i_24","x":64,"y":-30.5},{"frameNum":24},{"libName":"cbsmian","y":-27.3,"frameNum":2,"x":10.05,"d":0.6084,"mcName":"kj1atm","a":2.0849},{"frameNum":1},{"libName":"cbsmian","y":-27.3,"frameNum":2,"x":10.05,"d":0.6084,"mcName":"kj12atm","a":2.0849},{"frameNum":18},{"libName":"cbsmian","y":-46.6,"frameNum":2,"x":-10.3,"d":1.7189,"mcName":"kj2atm","a":0.9479},{"frameNum":28},{"libName":"i_46","b":0.8,"y":-30.74,"c":-0.8,"x":99.16,"d":0,"a":0},{"libName":"i_47","b":0.8,"y":-30.74,"c":-0.8,"x":99.16,"d":0,"a":0},{"libName":"i_48","b":0.8,"y":-28.35,"c":-0.8,"x":183.95,"d":0,"a":0},{"libName":"i_49","b":0.8,"y":-28.35,"c":-0.8,"x":183.95,"d":0,"a":0,"frameNum":1},{"libName":"i_50","b":0.8,"y":-37.15,"c":-0.8,"x":267.15,"d":0,"a":0,"frameNum":1},{"libName":"i_51","b":0.8,"y":-33.15,"c":-0.8,"x":267.15,"d":0,"a":0,"frameNum":1},{"libName":"i_52","b":0.8,"y":-27.55,"c":-0.8,"x":267.15,"d":0,"a":0,"frameNum":1},{"libName":"i_53","b":0.8,"y":-23.55,"c":-0.8,"x":267.15,"d":0,"a":0,"frameNum":1},{"libName":"i_54","b":0.8,"y":-18.75,"c":-0.8,"x":267.15,"d":0,"a":0,"frameNum":1},{"frameNum":22},{"libName":"i_55","b":-0.6014,"y":-24.82,"c":0.6014,"x":-12.99,"d":0.799,"a":0.799,"frameNum":7},{"frameNum":3,"libName":"zh2atm","x":26.95,"y":-6,"mcName":"zh2atm"},{"frameNum":46},{"libName":"i_24","x":29,"y":-30.5,"frameNum":1},{"libName":"i_25","x":28.25,"y":-18.65},{"libName":"i_93","x":26.35,"y":-24.75},{"x":33.75,"y":-39.5},{"x":41.1,"y":-54.3},{"x":46.4,"y":-64.8},{"x":51.65,"y":-75.35},{"libName":"i_97","x":54.2,"y":-81.85},{"x":56.85,"y":-87.15},{"libName":"i_98","x":65.7,"y":-89.1},{"libName":"i_97","x":58.95,"y":-91.35},{"libName":"i_98","x":81.2,"y":-95.4},{"x":94.15,"y":-100},{"libName":"i_99","x":100.1,"y":-103.85},{"x":109.05,"y":-107},{"libName":"i_100","x":116.1,"y":-110},{"x":120.1,"y":-111.4},{"x":124.05,"y":-112.8},{"x":125.05,"y":-113.15,"frameNum":2},{"x":129.75,"al":0.75,"d":1.9466,"y":-134.59,"a":0.5499},{"x":134.46,"al":0.5,"d":2.8933,"y":-156.02,"a":0.0997},{"frameNum":14},{"libName":"cbsmian","y":-31.35,"frameNum":1,"x":9.85,"d":0.76,"mcName":"sh1atm","a":0.389},{"frameNum":1},{"libName":"i_94","x":17.65,"y":-24.65,"frameNum":1},{"libName":"i_95","x":19.65,"y":-28.65,"frameNum":1},{"libName":"i_96","x":16.65,"y":-36.65,"frameNum":1},{"frameNum":17},{"libName":"cbsmian","y":-31.35,"frameNum":1,"x":9.85,"d":0.76,"mcName":"sh2atm","a":0.389},{"frameNum":5},{"libName":"cbsmian","y":-49.85,"frameNum":1,"x":-7.5,"d":1.4633,"mcName":"sh22atm","a":0.9334},{"frameNum":61},{"libName":"cbsmian","y":-90.8,"frameNum":2,"x":-47.2,"d":4.51,"mcName":"sbs1atm","a":2.2281},{"x":-47.2,"y":-90.8,"a":2.2281,"d":4.51,"mcName":"sbsatm","frameNum":2},{"frameNum":38},{"libName":"i_24","x":23.75,"y":-30.7,"frameNum":1},{"libName":"i_25","x":23,"y":-18.85,"frameNum":20},{"libName":"i_26","x":27.5,"y":-20},{"x":30.6,"y":-20},{"libName":"i_27","x":32.4,"y":-20.55},{"x":33,"y":-20.55,"frameNum":2},{"libName":"i_28","x":30.35,"y":-17.15},{"libName":"i_30","x":35.85,"y":-15.4},{"x":60.6,"y":-15.4},{"x":85.35,"y":-15.4},{"libName":"i_31","x":105.95,"y":-15.4},{"x":122.5,"y":-15.4},{"x":139,"y":-15.4},{"x":150,"y":-15.4},{"x":160.95,"y":-15.4},{"x":166.45,"y":-15.4},{"x":171.95,"y":-15.4},{"x":173.35,"y":-15.4,"frameNum":6},{"libName":"i_24","x":184.25,"y":-30.7,"frameNum":1},{"frameNum":17},{"libName":"i_93","x":209.4,"y":-24.95,"a":-1},{"x":204.95,"y":-26.05,"a":-1},{"x":200.5,"y":-27.15,"a":-1},{"libName":"i_97","x":197.2,"y":-27.4,"a":-1},{"x":192.75,"y":-28.5,"a":-1},{"libName":"i_98","x":181.05,"y":-28.4,"a":-1},{"x":176.6,"y":-29.5,"a":-1},{"libName":"i_99","x":177.15,"y":-30.65,"a":-1},{"x":172.7,"y":-31.75,"a":-1},{"libName":"i_100","x":168.2,"y":-33.35,"a":-1},{"x":167.7,"y":-31.35,"a":-1},{"x":167.2,"y":-29.35,"a":-1},{"x":166.7,"y":-27.35,"a":-1},{"x":166.2,"y":-25.35,"a":-1},{"x":165.7,"y":-23.35,"a":-1},{"libName":"i_145","x":135.75,"y":-10.05,"frameNum":6},{"libName":"i_93","x":159.4,"y":-24.95,"a":-1},{"x":163,"y":-42.95,"a":-1},{"x":166.6,"y":-60.95,"a":-1},{"x":169.4,"y":-74.95,"a":-1},{"x":172.2,"y":-88.95,"a":-1},{"x":174.2,"y":-98.95,"a":-1},{"x":176.2,"y":-108.95,"a":-1},{"x":177.4,"y":-114.95,"a":-1},{"x":178.6,"y":-120.95,"a":-1},{"x":179.2,"y":-123.95,"a":-1},{"frameNum":2,"x":179.4,"y":-124.95,"a":-1},{"libName":"i_146","x":193.45,"y":-123.55,"a":-1},{"x":186.1,"y":-118.35,"a":-1},{"libName":"i_147","x":178.5,"y":-114.15,"a":-1},{"x":171.15,"y":-108.9,"a":-1},{"libName":"i_148","x":163.8,"y":-104.7,"a":-1},{"x":156.4,"y":-99.5,"a":-1},{"libName":"i_149","x":149.05,"y":-93.8,"a":-1},{"x":141.7,"y":-88.6,"a":-1},{"x":134.3,"y":-83.35,"a":-1},{"x":126.95,"y":-78.15,"a":-1},{"x":119.55,"y":-72.95,"a":-1},{"x":112.2,"y":-67.75,"a":-1},{"x":104.85,"y":-62.5,"a":-1},{"x":97.45,"y":-57.3,"a":-1},{"x":90.1,"y":-52.1,"a":-1},{"x":82.7,"y":-46.9,"a":-1},{"x":75.35,"y":-41.7,"a":-1},{"x":67.95,"y":-36.45,"a":-1},{"x":60.6,"y":-31.25,"a":-1},{"libName":"i_150","x":45.75,"y":-18.55,"a":-1},{"x":54.65,"y":-20.55,"a":-1},{"x":63.55,"y":-22.55,"a":-1},{"x":72.4,"y":-24.55,"a":-1},{"x":81.3,"y":-26.55,"a":-1},{"x":90.2,"y":-28.55,"a":-1},{"x":99.1,"y":-30.55,"a":-1},{"x":107.95,"y":-32.55,"a":-1},{"x":116.85,"y":-34.55,"a":-1},{"x":125.75,"y":-36.55,"a":-1},{"x":134.65,"y":-38.55,"a":-1},{"x":143.5,"y":-40.55,"a":-1},{"x":152.4,"y":-42.55,"a":-1},{"x":161.3,"y":-44.55,"a":-1},{"x":170.2,"y":-46.55,"a":-1},{"x":179.05,"y":-48.55,"a":-1},{"x":187.95,"y":-50.55,"a":-1},{"x":196.85,"y":-52.55,"a":-1},{"frameNum":1,"x":205.75,"y":-54.55,"a":-1},{"frameNum":1},{"frameNum":1,"libName":"i_150","x":205.75,"y":-56.55,"a":-1},{"frameNum":1},{"frameNum":1,"libName":"i_150","x":205.75,"y":-58.55,"a":-1},{"frameNum":61},{"libName":"i_152","x":-47.45,"y":-85.9},{"libName":"i_153","x":-47.45,"y":-85.9},{"libName":"i_154","x":-47.45,"y":-82.9},{"libName":"i_155","x":-44.45,"y":-85.9},{"libName":"i_156","x":-47.45,"y":-85.9},{"libName":"i_157","x":-47.45,"y":-85.9},{"libName":"i_152","x":-47.45,"y":-85.9},{"libName":"i_153","x":-47.45,"y":-85.9},{"libName":"i_154","x":-47.45,"y":-82.9},{"libName":"i_155","x":-44.45,"y":-85.9},{"libName":"i_156","x":-47.45,"y":-85.9},{"libName":"i_157","x":-47.45,"y":-85.9},{"libName":"i_152","x":-47.45,"y":-85.9},{"libName":"i_153","x":-47.45,"y":-85.9},{"libName":"i_154","x":-47.45,"y":-82.9},{"libName":"i_155","x":-44.45,"y":-85.9},{"libName":"i_156","x":-47.45,"y":-85.9},{"libName":"i_157","x":-47.45,"y":-85.9},{"libName":"i_152","x":-47.45,"y":-85.9},{"libName":"i_153","x":-47.45,"y":-85.9},{"libName":"i_154","x":-47.45,"y":-82.9},{},{"libName":"i_158","x":-21.4,"y":-53.95,"frameNum":1},{"libName":"i_159","x":-30.4,"y":-120.95,"frameNum":1},{"libName":"i_160","x":-33.4,"y":-164.95,"frameNum":1},{},{"libName":"i_162","x":36.6,"y":-195.95,"frameNum":1},{"libName":"i_164","x":37.6,"y":-196.95,"frameNum":1},{"libName":"i_165","x":36.6,"y":-198.95,"frameNum":1},{"libName":"i_166","x":38.6,"y":-190.95,"frameNum":1},{"libName":"i_167","x":41.6,"y":-187.95,"frameNum":1},{"libName":"i_168","x":48.6,"y":-194.95,"frameNum":1},{"libName":"i_169","x":50.6,"y":-195.95,"frameNum":1},{"libName":"i_170","x":63.6,"y":-195.95,"frameNum":1},{"libName":"i_171","x":64.6,"y":-195.95,"frameNum":1},{"libName":"i_172","x":76.6,"y":-122.95,"frameNum":1},{"frameNum":32},{"libName":"i_39","x":-15.5,"y":-35.05,"frameNum":89},{"libName":"cbsmian","y":-32.75,"frameNum":57,"x":-13.55,"d":1.3763,"mcName":"bdmn","a":0.4035},{"frameNum":194}],[{"frameNum":107},{"libName":"cbsmian","y":-32.65,"frameNum":11,"x":-23.3,"d":0.8568,"mcName":"tz0atm","a":0.5911},{"frameNum":73},{"libName":"cbsmian","y":-16.8,"frameNum":1,"x":45.55,"d":0.4249,"mcName":"k31atm","a":0.5816},{"frameNum":4},{"libName":"cbsmian","y":-10.3,"frameNum":1,"x":62.55,"d":0.4249,"mcName":"k3atm","a":0.5816},{"frameNum":96},{"libName":"cbsmian","y":-30.8,"frameNum":1,"x":6.3,"d":0.9958,"mcName":"zh1atm","a":1.4465},{"x":10.3,"y":-35.8,"a":2.5914,"d":1.4519,"mcName":"zh1atm","frameNum":1},{"x":9.85,"y":-42.9,"a":3.9253,"d":1.6257,"mcName":"zh1atm","frameNum":1},{"frameNum":93},{"libName":"i_94","x":27.65,"y":-24.65,"frameNum":1},{"libName":"i_95","x":29.65,"y":-28.65,"frameNum":1},{"libName":"i_96","x":26.65,"y":-36.65,"frameNum":1},{"frameNum":3},{"libName":"cbsmian","y":-97,"frameNum":1,"x":87.25,"d":0.76,"mcName":"zh3atm","a":0.7447},{"x":117.25,"y":-104.5,"a":0.7447,"d":0.76,"mcName":"zh3atm","frameNum":1},{"x":119.75,"y":-107.5,"a":0.7447,"d":0.76,"mcName":"zh3atm","frameNum":1},{"frameNum":24},{"libName":"cbsmian","y":-37.4,"frameNum":1,"x":9.85,"d":1.3408,"mcName":"sh12atm","a":0.4496},{"frameNum":91},{"x":-104.45,"libName":"mc_6","b":0.6912,"y":13.9,"c":0.6912,"blendMode":"screen","d":-0.6729,"a":0.6729,"frameNum":30},{"frameNum":37},{"libName":"cbsmian","y":-18.35,"frameNum":2,"x":27.35,"d":0.5754,"mcName":"bs1atm","a":0.7967},{"frameNum":3},{"libName":"i_136","y":-16.37,"x":15.23,"al":0.82,"d":0.3611,"a":0.7514},{"libName":"i_137","y":-14.6,"x":11.42,"al":0.82,"d":0.2997,"a":0.9747},{"libName":"i_138","y":-13.19,"x":8.27,"al":0.82,"d":0.2448,"a":1.1745},{"libName":"i_139","y":-11.86,"x":25.56,"al":0.82,"d":0.1962,"a":1.3508},{"libName":"i_140","y":-7.83,"x":38.34,"al":0.82,"d":0.1543,"a":1.5036},{"libName":"i_141","y":-6.58,"x":34.12,"al":0.82,"d":0.1187,"a":1.6329},{"libName":"i_142","y":-5.85,"x":43.79,"al":0.82,"d":0.0896,"a":1.7386},{"libName":"i_143","y":-5.28,"x":40.82,"al":0.82,"d":0.067,"a":1.8209},{"libName":"i_136","y":-4.59,"x":49.91,"al":0.82,"d":0.0508,"a":1.8797},{"libName":"i_137","y":-4.24,"x":29.94,"al":0.82,"d":0.0411,"a":1.9149},{"libName":"i_136","y":-4.15,"x":47.44,"al":0.82,"d":0.0379,"a":1.9267},{"frameNum":32},{"libName":"cbsmian","y":-17.85,"frameNum":2,"x":112.35,"d":0.7977,"mcName":"bs3atm","a":1.3433},{"frameNum":13},{"libName":"cbsmian","y":-49.85,"frameNum":2,"x":-21.5,"d":1.7973,"mcName":"bs4atm","a":1.1004},{"frameNum":11},{"libName":"cbsmian","y":-117.85,"frameNum":2,"x":77.5,"d":1.8905,"mcName":"bs5atm","a":1.4087},{"frameNum":11},{"libName":"cbsmian","y":-34.95,"frameNum":2,"x":-5,"d":1.5468,"mcName":"bsatm","a":0.7184},{"frameNum":109},{"libName":"i_158","x":-110.4,"y":-53.95,"frameNum":1},{"libName":"i_159","x":-119.4,"y":-120.95,"frameNum":1},{},{"libName":"i_161","x":-40.4,"y":-183.95,"frameNum":1},{"libName":"i_162","x":-43.4,"y":-195.95,"frameNum":1},{"libName":"i_164","x":-42.4,"y":-196.95,"frameNum":1},{"libName":"i_165","x":-43.4,"y":-198.95,"frameNum":1},{"libName":"i_166","x":-41.4,"y":-190.95,"frameNum":1},{"libName":"i_167","x":-38.4,"y":-187.95,"frameNum":1},{"libName":"i_168","x":-31.4,"y":-194.95,"frameNum":1},{"libName":"i_169","x":-29.4,"y":-195.95,"frameNum":1},{"libName":"i_170","x":-16.4,"y":-195.95,"frameNum":1},{"libName":"i_171","x":-15.4,"y":-195.95,"frameNum":1},{"libName":"i_172","x":-3.4,"y":-122.95},{"frameNum":375}],[{"libName":"cbsmian","y":-32.75,"frameNum":265,"x":-13.55,"d":1.3763,"mcName":"bdmn","a":0.4035},{"frameNum":133},{"libName":"cbsmian","y":-22.85,"frameNum":1,"x":28.75,"d":0.76,"mcName":"zh31atm","a":0.389},{"frameNum":132},{"x":-80,"libName":"mc_7","b":1,"y":-44.05,"c":1,"blendMode":"screen","d":0,"a":0,"frameNum":30},{"frameNum":46},{"libName":"cbsmian","y":-12.85,"frameNum":2,"x":42.35,"d":0.5754,"mcName":"bs2atm","a":2.2529},{"frameNum":199},{"libName":"i_158","x":-195.4,"y":-53.95,"frameNum":1},{},{"libName":"i_160","x":-122.4,"y":-164.95,"frameNum":1},{"libName":"i_161","x":-129.4,"y":-183.95,"frameNum":1},{"libName":"i_162","x":-132.4,"y":-195.95,"frameNum":1},{"libName":"i_164","x":-131.4,"y":-196.95,"frameNum":1},{"libName":"i_165","x":-132.4,"y":-198.95,"frameNum":1},{"libName":"i_166","x":-130.4,"y":-190.95,"frameNum":1},{"libName":"i_167","x":-127.4,"y":-187.95,"frameNum":1},{"libName":"i_168","x":-120.4,"y":-194.95,"frameNum":1},{"libName":"i_169","x":-118.4,"y":-195.95,"frameNum":1},{"libName":"i_170","x":-105.4,"y":-195.95,"frameNum":1},{"libName":"i_171","x":-104.4,"y":-195.95,"frameNum":1},{"frameNum":375}],[{"frameNum":268},{"libName":"cbsmian","y":-32.75,"frameNum":225,"x":-13.55,"d":1.3763,"mcName":"bdmn","a":0.4035},{"frameNum":39},{"libName":"cbsmian","y":-32.75,"frameNum":43,"x":-13.55,"d":1.3763,"mcName":"bdmn","a":0.4035},{"x":-14.05,"y":-39.85,"a":0.4035,"d":1.5523,"mcName":"bdmn","frameNum":1},{"frameNum":20},{"libName":"cbsmian","y":-32.75,"frameNum":141,"x":-13.55,"d":1.3763,"mcName":"bdmn","a":0.4035},{"frameNum":73},{"libName":"i_159","x":-204.4,"y":-120.95,"frameNum":1},{"libName":"i_160","x":-207.4,"y":-164.95,"frameNum":1},{"libName":"i_161","x":-214.4,"y":-183.95,"frameNum":1},{"libName":"i_162","x":-217.4,"y":-195.95,"frameNum":1},{"libName":"i_164","x":-216.4,"y":-196.95,"frameNum":1},{"libName":"i_165","x":-217.4,"y":-198.95,"frameNum":1},{"libName":"i_166","x":-215.4,"y":-190.95,"frameNum":1},{"libName":"i_167","x":-212.4,"y":-187.95,"frameNum":1},{"libName":"i_168","x":-205.4,"y":-194.95,"frameNum":1},{"libName":"i_169","x":-203.4,"y":-195.95,"frameNum":1},{"libName":"i_170","x":-190.4,"y":-195.95,"frameNum":1},{"libName":"i_171","x":-189.4,"y":-195.95},{"frameNum":375}],[{"frameNum":816},{"libName":"i_158","x":-271.4,"y":-53.95,"frameNum":1},{"libName":"i_159","x":-280.4,"y":-120.95,"frameNum":1},{"libName":"i_160","x":-283.4,"y":-164.95,"frameNum":1},{"libName":"i_161","x":-290.4,"y":-183.95,"frameNum":1},{"libName":"i_162","x":-293.4,"y":-195.95,"frameNum":1},{"libName":"i_164","x":-292.4,"y":-196.95,"frameNum":1},{"libName":"i_165","x":-293.4,"y":-198.95,"frameNum":1},{"libName":"i_166","x":-291.4,"y":-190.95,"frameNum":1},{"libName":"i_167","x":-288.4,"y":-187.95,"frameNum":1},{"libName":"i_168","x":-281.4,"y":-194.95,"frameNum":1},{"libName":"i_169","x":-279.4,"y":-195.95,"frameNum":1},{"libName":"i_170","x":-266.4,"y":-195.95,"frameNum":1},{"frameNum":375}],[{"frameNum":812},{"libName":"i_29","x":-14.25,"y":-31.2,"frameNum":60},{"frameNum":342}],[{"frameNum":812},{"libName":"i_155","x":-44.45,"y":-85.9},{"libName":"i_156","x":-47.45,"y":-85.9},{"libName":"i_157","x":-47.45,"y":-85.9},{"libName":"i_152","x":-47.45,"y":-85.9},{"libName":"i_153","x":-47.45,"y":-85.9},{"libName":"i_154","x":-47.45,"y":-82.9},{"libName":"i_155","x":-44.45,"y":-85.9},{"libName":"i_156","x":-47.45,"y":-85.9},{"libName":"i_157","x":-47.45,"y":-85.9},{"frameNum":394}]],"screenH":640,"frameLabels":{"招1":{"end":338,"begin":297},"招2":{"end":396,"begin":338},"走":{"end":32,"begin":9},"摔2":{"end":495,"begin":463},"跳":{"end":62,"begin":57},"超必杀":{"end":991,"begin":744},"砍2":{"end":185,"begin":165},"跳招0":{"end":120,"begin":113},"开场":{"end":1157,"begin":1100},"落地":{"end":89,"begin":72},"防御":{"end":997,"begin":991},"防御恢复":{"end":1009,"begin":997},"跳招21":{"end":144,"begin":120},"击飞":{"end":1027,"begin":1022},"砍1":{"end":165,"begin":144},"跳招":{"end":113,"begin":108},"砍3":{"end":232,"begin":185},"招32":{"end":435,"begin":400},"砍技2":{"end":297,"begin":266},"必杀":{"end":648,"begin":579},"站立":{"end":9,"begin":0},"瞬步":{"end":52,"begin":32},"击飞_起":{"end":1077,"begin":1055},"击飞_弹":{"end":1046,"begin":1037},"跳中":{"end":67,"begin":62},"被打":{"end":1022,"begin":1009},"起跳":{"end":57,"begin":52},"击飞_落":{"end":1037,"begin":1027},"摔1":{"end":463,"begin":435},"起身":{"end":1100,"begin":1077},"失败":{"begin":1187},"上必杀":{"end":579,"begin":495},"必杀2":{"end":744,"begin":648},"胜利":{"end":1187,"begin":1157},"招3":{"end":400,"begin":396},"落":{"end":72,"begin":67},"击飞_倒":{"end":1055,"begin":1046},"砍技1":{"end":266,"begin":232},"跳砍":{"end":108,"begin":89}},"totalFrame":1217},"wk":{"direction":1,"stageHeight":164.95,"frameTime":33,"soundObj":{"40":[{"libName":"l_26"}]},"layers":[[{"libName":"i_163","x":-370.95,"y":-153.55},{"libName":"i_175","x":-359.5,"y":-161.55,"frameNum":2},{"libName":"i_177","x":-375.95,"y":-155.65,"frameNum":2},{"libName":"i_178","x":-378.45,"y":-151.55,"frameNum":2},{"libName":"i_163","x":-370.95,"y":-153.55,"frameNum":2},{"libName":"i_175","x":-359.5,"y":-161.55,"frameNum":2},{"libName":"i_177","x":-375.95,"y":-155.65,"frameNum":2},{"libName":"i_178","x":-378.45,"y":-151.55,"frameNum":2},{"libName":"i_163","x":-370.95,"y":-153.55,"frameNum":2},{"libName":"i_175","x":-359.5,"y":-161.55,"frameNum":2},{"libName":"i_177","x":-375.95,"y":-155.65,"frameNum":2},{"libName":"i_178","x":-378.45,"y":-151.55,"frameNum":2},{"libName":"i_163","x":-370.95,"y":-153.55,"frameNum":2},{"libName":"i_175","x":-359.5,"y":-161.55,"frameNum":2},{"libName":"i_177","x":-375.95,"y":-155.65,"frameNum":2},{"libName":"i_178","x":-378.45,"y":-151.55,"frameNum":2},{},{"libName":"i_179","y":-87.75,"x":-441.6,"d":0.7,"a":0.7,"frameNum":1},{"libName":"i_180","y":-94.75,"x":-440.9,"d":0.7,"a":0.7,"frameNum":1},{"libName":"i_181","y":-96.15,"x":-447.9,"d":0.7,"a":0.7,"frameNum":1},{"libName":"i_182","y":-110.15,"x":-449.3,"d":0.7,"a":0.7,"frameNum":1},{"libName":"i_183","y":-114.35,"x":-450,"d":0.7,"a":0.7,"frameNum":1},{"libName":"i_184","y":-111.55,"x":-450.7,"d":0.7,"a":0.7,"frameNum":1},{"libName":"i_185","y":-116.45,"x":-448.6,"d":0.7,"a":0.7,"frameNum":1},{"libName":"i_186","y":-115.05,"x":-447.2,"d":0.7,"a":0.7,"frameNum":1},{"libName":"i_187","y":-115.05,"x":-447.2,"d":0.7,"a":0.7,"frameNum":1},{"libName":"i_188","y":-114.35,"x":-448.6,"d":0.7,"a":0.7,"frameNum":1},{"libName":"i_189","y":-112.95,"x":-446.5,"d":0.7,"a":0.7,"frameNum":1},{"libName":"i_190","y":-112.95,"x":-447.9,"d":0.7,"a":0.7,"frameNum":1},{"libName":"i_191","y":-111.55,"x":-447.9,"d":0.7,"a":0.7,"frameNum":1},{"libName":"i_192","y":-112.25,"x":-449.3,"d":0.7,"a":0.7,"frameNum":1},{"libName":"i_193","y":-110.15,"x":-448.6,"d":0.7,"a":0.7,"frameNum":1},{"libName":"i_194","y":-109.45,"x":-445.1,"d":0.7,"a":0.7,"frameNum":1},{"libName":"i_195","y":-109.45,"x":-442.3,"d":0.7,"a":0.7,"frameNum":1},{"libName":"i_196","y":-110.15,"x":-440.2,"d":0.7,"a":0.7,"frameNum":1},{"libName":"i_197","y":-111.55,"x":-443,"d":0.7,"a":0.7,"frameNum":1},{"libName":"i_198","y":-104.55,"x":-443.7,"d":0.7,"a":0.7,"frameNum":1},{"libName":"i_199","y":-98.95,"x":-422.7,"d":0.7,"a":0.7,"frameNum":1},{"frameNum":1}],[{"libName":"i_173","x":-78.45,"y":-48.55,"frameNum":1},{"frameNum":44},{"libName":"i_180","y":-118.35,"x":-371.3,"d":0.9,"a":0.9,"frameNum":1},{"libName":"i_181","y":-120.15,"x":-380.3,"d":0.9,"a":0.9,"frameNum":1},{"libName":"i_182","y":-138.15,"x":-382.1,"d":0.9,"a":0.9,"frameNum":1},{"libName":"i_183","y":-143.55,"x":-383,"d":0.9,"a":0.9,"frameNum":1},{"libName":"i_184","y":-139.95,"x":-383.9,"d":0.9,"a":0.9,"frameNum":1},{"libName":"i_185","y":-146.25,"x":-381.2,"d":0.9,"a":0.9,"frameNum":1},{"libName":"i_186","y":-144.45,"x":-379.4,"d":0.9,"a":0.9,"frameNum":1},{"libName":"i_187","y":-144.45,"x":-379.4,"d":0.9,"a":0.9,"frameNum":1},{"libName":"i_188","y":-143.55,"x":-381.2,"d":0.9,"a":0.9,"frameNum":1},{"libName":"i_189","y":-141.75,"x":-378.5,"d":0.9,"a":0.9,"frameNum":1},{"libName":"i_190","y":-141.75,"x":-380.3,"d":0.9,"a":0.9,"frameNum":1},{"libName":"i_191","y":-139.95,"x":-380.3,"d":0.9,"a":0.9,"frameNum":1},{"libName":"i_192","y":-140.85,"x":-382.1,"d":0.9,"a":0.9,"frameNum":1},{"libName":"i_193","y":-138.15,"x":-381.2,"d":0.9,"a":0.9,"frameNum":1},{"libName":"i_194","y":-137.25,"x":-376.7,"d":0.9,"a":0.9,"frameNum":1},{"libName":"i_195","y":-137.25,"x":-373.1,"d":0.9,"a":0.9,"frameNum":1},{"libName":"i_196","y":-138.15,"x":-370.4,"d":0.9,"a":0.9,"frameNum":1},{"libName":"i_197","y":-139.95,"x":-374,"d":0.9,"a":0.9,"frameNum":1},{"libName":"i_198","y":-130.95,"x":-374.9,"d":0.9,"a":0.9,"frameNum":1},{"libName":"i_199","y":-123.75,"x":-347.9,"d":0.9,"a":0.9,"frameNum":1},{"frameNum":3}],[{"libName":"i_173","x":-198.45,"y":-46.55,"frameNum":1},{"frameNum":44},{"libName":"i_181","y":-152.15,"x":-296.7,"d":1.1,"a":1.1,"frameNum":1},{"libName":"i_182","y":-174.15,"x":-298.9,"d":1.1,"a":1.1,"frameNum":1},{"libName":"i_183","y":-180.75,"x":-300,"d":1.1,"a":1.1,"frameNum":1},{"libName":"i_184","y":-176.35,"x":-301.1,"d":1.1,"a":1.1,"frameNum":1},{"libName":"i_185","y":-184.05,"x":-297.8,"d":1.1,"a":1.1,"frameNum":1},{"libName":"i_186","y":-181.85,"x":-295.6,"d":1.1,"a":1.1,"frameNum":1},{"libName":"i_187","y":-181.85,"x":-295.6,"d":1.1,"a":1.1,"frameNum":1},{"libName":"i_188","y":-180.75,"x":-297.8,"d":1.1,"a":1.1,"frameNum":1},{"libName":"i_189","y":-178.55,"x":-294.5,"d":1.1,"a":1.1,"frameNum":1},{"libName":"i_190","y":-178.55,"x":-296.7,"d":1.1,"a":1.1,"frameNum":1},{"libName":"i_191","y":-176.35,"x":-296.7,"d":1.1,"a":1.1,"frameNum":1},{"libName":"i_192","y":-177.45,"x":-298.9,"d":1.1,"a":1.1,"frameNum":1},{"libName":"i_193","y":-174.15,"x":-297.8,"d":1.1,"a":1.1,"frameNum":1},{"libName":"i_194","y":-173.05,"x":-292.3,"d":1.1,"a":1.1,"frameNum":1},{"libName":"i_195","y":-173.05,"x":-287.9,"d":1.1,"a":1.1,"frameNum":1},{"libName":"i_196","y":-174.15,"x":-284.6,"d":1.1,"a":1.1,"frameNum":1},{"libName":"i_197","y":-176.35,"x":-289,"d":1.1,"a":1.1,"frameNum":1},{"libName":"i_198","y":-165.35,"x":-290.1,"d":1.1,"a":1.1,"frameNum":1},{"libName":"i_199","y":-156.55,"x":-257.1,"d":1.1,"a":1.1,"frameNum":1},{"frameNum":5}],[{"libName":"i_173","y":-45.6,"x":-324.55,"d":1,"a":1,"frameNum":1},{"frameNum":44},{"libName":"i_182","y":-210.15,"x":-207.7,"d":1.3,"a":1.3,"frameNum":1},{"libName":"i_183","y":-217.95,"x":-209,"d":1.3,"a":1.3,"frameNum":1},{"libName":"i_184","y":-212.75,"x":-210.3,"d":1.3,"a":1.3,"frameNum":1},{"libName":"i_185","y":-221.85,"x":-206.4,"d":1.3,"a":1.3,"frameNum":1},{"libName":"i_186","y":-219.25,"x":-203.8,"d":1.3,"a":1.3,"frameNum":1},{"libName":"i_187","y":-219.25,"x":-203.8,"d":1.3,"a":1.3,"frameNum":1},{"libName":"i_188","y":-217.95,"x":-206.4,"d":1.3,"a":1.3,"frameNum":1},{"libName":"i_189","y":-215.35,"x":-202.5,"d":1.3,"a":1.3,"frameNum":1},{"libName":"i_190","y":-215.35,"x":-205.1,"d":1.3,"a":1.3,"frameNum":1},{"libName":"i_191","y":-212.75,"x":-205.1,"d":1.3,"a":1.3,"frameNum":1},{"libName":"i_192","y":-214.05,"x":-207.7,"d":1.3,"a":1.3,"frameNum":1},{"libName":"i_193","y":-210.15,"x":-206.4,"d":1.3,"a":1.3,"frameNum":1},{"libName":"i_194","y":-208.85,"x":-199.9,"d":1.3,"a":1.3,"frameNum":1},{"libName":"i_195","y":-208.85,"x":-194.7,"d":1.3,"a":1.3,"frameNum":1},{"libName":"i_196","y":-210.15,"x":-190.8,"d":1.3,"a":1.3,"frameNum":1},{"libName":"i_197","y":-212.75,"x":-196,"d":1.3,"a":1.3,"frameNum":1},{"libName":"i_198","y":-199.75,"x":-197.3,"d":1.3,"a":1.3,"frameNum":1},{"libName":"i_199","y":-189.35,"x":-158.3,"d":1.3,"a":1.3,"frameNum":1},{"frameNum":7}],[{"libName":"i_174","x":-402.5,"y":-51.45,"frameNum":1},{"x":-86.45,"y":-49.55,"frameNum":1},{"frameNum":42},{"libName":"i_183","y":-195.35,"x":-85.5,"d":1.1999,"a":1.2,"frameNum":1},{"libName":"i_184","y":-190.55,"x":-86.7,"d":1.1999,"a":1.2,"frameNum":1},{"libName":"i_185","y":-198.95,"x":-83.1,"d":1.1999,"a":1.2,"frameNum":1},{"libName":"i_186","y":-196.55,"x":-80.7,"d":1.1999,"a":1.2,"frameNum":1},{"libName":"i_187","y":-196.55,"x":-80.7,"d":1.1999,"a":1.2,"frameNum":1},{"libName":"i_188","y":-195.35,"x":-83.1,"d":1.1999,"a":1.2,"frameNum":1},{"libName":"i_189","y":-192.95,"x":-79.5,"d":1.1999,"a":1.2,"frameNum":1},{"libName":"i_190","y":-192.95,"x":-81.9,"d":1.1999,"a":1.2,"frameNum":1},{"libName":"i_191","y":-190.55,"x":-81.9,"d":1.1999,"a":1.2,"frameNum":1},{"libName":"i_192","y":-191.75,"x":-84.3,"d":1.1999,"a":1.2,"frameNum":1},{"libName":"i_193","y":-188.15,"x":-83.1,"d":1.1999,"a":1.2,"frameNum":1},{"libName":"i_194","y":-186.95,"x":-77.1,"d":1.1999,"a":1.2,"frameNum":1},{"libName":"i_195","y":-186.95,"x":-72.3,"d":1.1999,"a":1.2,"frameNum":1},{"libName":"i_196","y":-188.15,"x":-68.7,"d":1.1999,"a":1.2,"frameNum":1},{"libName":"i_197","y":-190.55,"x":-73.5,"d":1.1999,"a":1.2,"frameNum":1},{"libName":"i_198","y":-178.55,"x":-74.7,"d":1.1999,"a":1.2,"frameNum":1},{"libName":"i_199","y":-168.95,"x":-38.7,"d":1.1999,"a":1.2,"frameNum":1},{"frameNum":9}],[{"libName":"i_174","x":-152.5,"y":-49.45,"frameNum":1},{"x":-206.45,"y":-47.55,"frameNum":1},{"frameNum":86}],[{"libName":"i_174","y":-48.5,"x":-268.6,"d":1,"a":1,"frameNum":1},{"frameNum":1,"x":-332.55,"d":1,"y":-46.6,"a":1},{"frameNum":86}],[{"libName":"i_174","x":-335.55,"y":-77.5,"frameNum":1},{"libName":"i_176","x":-408.5,"y":-51.45,"frameNum":1},{"x":-92.45,"y":-49.55,"frameNum":1},{"frameNum":84}],[{"libName":"i_174","x":-115.55,"y":-75.5,"frameNum":1},{"libName":"i_176","x":-158.5,"y":-49.45,"frameNum":1},{"x":-212.45,"y":-47.55,"frameNum":1},{"frameNum":84}],[{"libName":"i_174","y":-74.55,"x":-221.65,"d":1,"a":1,"frameNum":1},{"libName":"i_176","y":-48.5,"x":-274.6,"d":1,"a":1,"frameNum":1},{"frameNum":1,"x":-338.55,"d":1,"y":-46.6,"a":1},{"frameNum":84}],[{"frameNum":1},{"libName":"i_176","x":-341.55,"y":-77.5,"frameNum":1},{"libName":"i_173","x":-394.5,"y":-50.45,"frameNum":1},{"x":-78.45,"y":-48.55,"frameNum":1},{"frameNum":82}],[{"frameNum":1},{"libName":"i_176","x":-121.55,"y":-75.5,"frameNum":1},{"libName":"i_173","x":-144.5,"y":-48.45,"frameNum":1},{"x":-198.45,"y":-46.55,"frameNum":1},{"frameNum":82}],[{"frameNum":1},{"libName":"i_176","y":-74.55,"x":-227.65,"d":1,"a":1,"frameNum":1},{"libName":"i_173","y":-47.5,"x":-260.6,"d":1,"a":1,"frameNum":1},{"frameNum":1,"x":-324.55,"d":1,"y":-45.6,"a":1},{"frameNum":82}],[{"frameNum":3},{"libName":"i_173","x":-327.55,"y":-76.5,"frameNum":1},{"libName":"i_174","x":-402.5,"y":-51.45,"frameNum":1},{"x":-86.45,"y":-49.55,"frameNum":1},{"frameNum":80}],[{"frameNum":3},{"libName":"i_173","x":-107.55,"y":-74.5,"frameNum":1},{"libName":"i_174","x":-152.5,"y":-49.45,"frameNum":1},{"x":-206.45,"y":-47.55,"frameNum":1},{"frameNum":80}],[{"frameNum":3},{"libName":"i_173","y":-73.55,"x":-213.65,"d":1,"a":1,"frameNum":1},{"libName":"i_174","y":-48.5,"x":-268.6,"d":1,"a":1,"frameNum":1},{"frameNum":1,"x":-332.55,"d":1,"y":-46.6,"a":1},{"frameNum":80}],[{"frameNum":5},{"libName":"i_174","x":-335.55,"y":-77.5,"frameNum":1},{"libName":"i_176","x":-408.5,"y":-51.45,"frameNum":1},{"x":-92.45,"y":-49.55,"frameNum":1},{"frameNum":78}],[{"frameNum":5},{"libName":"i_174","x":-115.55,"y":-75.5,"frameNum":1},{"libName":"i_176","x":-158.5,"y":-49.45,"frameNum":1},{"x":-212.45,"y":-47.55,"frameNum":1},{"frameNum":78}],[{"frameNum":5},{"libName":"i_174","y":-74.55,"x":-221.65,"d":1,"a":1,"frameNum":1},{"libName":"i_176","y":-48.5,"x":-274.6,"d":1,"a":1,"frameNum":1},{"frameNum":1,"x":-338.55,"d":1,"y":-46.6,"a":1},{"frameNum":78}],[{"frameNum":7},{"libName":"i_176","x":-341.55,"y":-77.5,"frameNum":1},{"libName":"i_173","x":-394.5,"y":-50.45,"frameNum":1},{"x":-78.45,"y":-48.55,"frameNum":1},{"frameNum":76}],[{"frameNum":7},{"libName":"i_176","x":-121.55,"y":-75.5,"frameNum":1},{"libName":"i_173","x":-144.5,"y":-48.45,"frameNum":1},{"x":-198.45,"y":-46.55,"frameNum":1},{"frameNum":76}],[{"frameNum":7},{"libName":"i_176","y":-74.55,"x":-227.65,"d":1,"a":1,"frameNum":1},{"libName":"i_173","y":-47.5,"x":-260.6,"d":1,"a":1,"frameNum":1},{"frameNum":1,"x":-324.55,"d":1,"y":-45.6,"a":1},{"frameNum":76}],[{"frameNum":9},{"libName":"i_173","x":-327.55,"y":-76.5,"frameNum":1},{"libName":"i_174","x":-402.5,"y":-51.45,"frameNum":1},{"x":-86.45,"y":-49.55,"frameNum":1},{"frameNum":74}],[{"frameNum":9},{"libName":"i_173","x":-107.55,"y":-74.5,"frameNum":1},{"libName":"i_174","x":-152.5,"y":-49.45,"frameNum":1},{"x":-206.45,"y":-47.55,"frameNum":1},{"frameNum":74}],[{"frameNum":9},{"libName":"i_173","y":-73.55,"x":-213.65,"d":1,"a":1,"frameNum":1},{"libName":"i_174","y":-48.5,"x":-268.6,"d":1,"a":1,"frameNum":1},{"frameNum":1,"x":-332.55,"d":1,"y":-46.6,"a":1},{"frameNum":74}],[{"frameNum":11},{"libName":"i_174","x":-335.55,"y":-77.5,"frameNum":1},{"libName":"i_176","x":-408.5,"y":-51.45,"frameNum":1},{"x":-92.45,"y":-49.55,"frameNum":1},{"frameNum":72}],[{"frameNum":11},{"libName":"i_174","x":-115.55,"y":-75.5,"frameNum":1},{"libName":"i_176","x":-158.5,"y":-49.45,"frameNum":1},{"x":-212.45,"y":-47.55,"frameNum":1},{"frameNum":72}],[{"frameNum":11},{"libName":"i_174","y":-74.55,"x":-221.65,"d":1,"a":1,"frameNum":1},{"libName":"i_176","y":-48.5,"x":-274.6,"d":1,"a":1,"frameNum":1},{"frameNum":1,"x":-338.55,"d":1,"y":-46.6,"a":1},{"frameNum":72}],[{"frameNum":13},{"libName":"i_176","x":-341.55,"y":-77.5,"frameNum":1},{"libName":"i_173","x":-394.5,"y":-50.45,"frameNum":1},{"x":-78.45,"y":-48.55,"frameNum":1},{"frameNum":70}],[{"frameNum":13},{"libName":"i_176","x":-121.55,"y":-75.5,"frameNum":1},{"libName":"i_173","x":-144.5,"y":-48.45,"frameNum":1},{"x":-198.45,"y":-46.55,"frameNum":1},{"frameNum":70}],[{"frameNum":13},{"libName":"i_176","y":-74.55,"x":-227.65,"d":1,"a":1,"frameNum":1},{"libName":"i_173","y":-47.5,"x":-260.6,"d":1,"a":1,"frameNum":1},{"frameNum":1,"x":-324.55,"d":1,"y":-45.6,"a":1},{"frameNum":70}],[{"frameNum":15},{"libName":"i_173","x":-327.55,"y":-76.5,"frameNum":1},{"libName":"i_174","x":-402.5,"y":-51.45,"frameNum":1},{"x":-86.45,"y":-49.55,"frameNum":1},{"frameNum":68}],[{"frameNum":15},{"libName":"i_173","x":-107.55,"y":-74.5,"frameNum":1},{"libName":"i_174","x":-152.5,"y":-49.45,"frameNum":1},{"x":-206.45,"y":-47.55,"frameNum":1},{"frameNum":68}],[{"frameNum":15},{"libName":"i_173","y":-73.55,"x":-213.65,"d":1,"a":1,"frameNum":1},{"libName":"i_174","y":-48.5,"x":-268.6,"d":1,"a":1,"frameNum":1},{"frameNum":1,"x":-332.55,"d":1,"y":-46.6,"a":1},{"frameNum":68}],[{"frameNum":17},{"libName":"i_174","x":-335.55,"y":-77.5,"frameNum":1},{"libName":"i_176","x":-408.5,"y":-51.45,"frameNum":1},{"x":-92.45,"y":-49.55,"frameNum":1},{"frameNum":66}],[{"frameNum":17},{"libName":"i_174","x":-115.55,"y":-75.5,"frameNum":1},{"libName":"i_176","x":-158.5,"y":-49.45,"frameNum":1},{"x":-212.45,"y":-47.55,"frameNum":1},{"frameNum":66}],[{"frameNum":17},{"libName":"i_174","y":-74.55,"x":-221.65,"d":1,"a":1,"frameNum":1},{"libName":"i_176","y":-48.5,"x":-274.6,"d":1,"a":1,"frameNum":1},{"frameNum":1,"x":-338.55,"d":1,"y":-46.6,"a":1},{"frameNum":66}],[{"frameNum":19},{"libName":"i_176","x":-341.55,"y":-77.5,"frameNum":1},{"libName":"i_173","x":-394.5,"y":-50.45,"frameNum":1},{"x":-78.45,"y":-48.55,"frameNum":1},{"frameNum":64}],[{"frameNum":19},{"libName":"i_176","x":-121.55,"y":-75.5,"frameNum":1},{"libName":"i_173","x":-144.5,"y":-48.45,"frameNum":1},{"x":-198.45,"y":-46.55,"frameNum":1},{"frameNum":64}],[{"frameNum":19},{"libName":"i_176","y":-74.55,"x":-227.65,"d":1,"a":1,"frameNum":1},{"libName":"i_173","y":-47.5,"x":-260.6,"d":1,"a":1,"frameNum":1},{"frameNum":1,"x":-324.55,"d":1,"y":-45.6,"a":1},{"frameNum":64}],[{"frameNum":21},{"libName":"i_173","x":-327.55,"y":-76.5,"frameNum":1},{"libName":"i_174","x":-402.5,"y":-51.45,"frameNum":1},{"x":-86.45,"y":-49.55,"frameNum":1},{"frameNum":62}],[{"frameNum":21},{"libName":"i_173","x":-107.55,"y":-74.5,"frameNum":1},{"libName":"i_174","x":-152.5,"y":-49.45,"frameNum":1},{"x":-206.45,"y":-47.55,"frameNum":1},{"frameNum":62}],[{"frameNum":21},{"libName":"i_173","y":-73.55,"x":-213.65,"d":1,"a":1,"frameNum":1},{"libName":"i_174","y":-48.5,"x":-268.6,"d":1,"a":1,"frameNum":1},{"frameNum":1,"x":-332.55,"d":1,"y":-46.6,"a":1},{"frameNum":62}],[{"frameNum":23},{"libName":"i_174","x":-335.55,"y":-77.5,"frameNum":1},{"libName":"i_176","x":-408.5,"y":-51.45,"frameNum":1},{"x":-92.45,"y":-49.55,"frameNum":1},{"frameNum":60}],[{"frameNum":23},{"libName":"i_174","x":-115.55,"y":-75.5,"frameNum":1},{"libName":"i_176","x":-158.5,"y":-49.45,"frameNum":1},{"x":-212.45,"y":-47.55,"frameNum":1},{"frameNum":60}],[{"frameNum":23},{"libName":"i_174","y":-74.55,"x":-221.65,"d":1,"a":1,"frameNum":1},{"libName":"i_176","y":-48.5,"x":-274.6,"d":1,"a":1,"frameNum":1},{"frameNum":1,"x":-338.55,"d":1,"y":-46.6,"a":1},{"frameNum":60}],[{"frameNum":25},{"libName":"i_176","x":-341.55,"y":-77.5,"frameNum":1},{"libName":"i_173","x":-394.5,"y":-50.45,"frameNum":1},{"x":-78.45,"y":-48.55,"frameNum":1},{"frameNum":58}],[{"frameNum":25},{"libName":"i_176","x":-121.55,"y":-75.5,"frameNum":1},{"libName":"i_173","x":-144.5,"y":-48.45,"frameNum":1},{"x":-198.45,"y":-46.55,"frameNum":1},{"frameNum":58}],[{"frameNum":25},{"libName":"i_176","y":-74.55,"x":-227.65,"d":1,"a":1,"frameNum":1},{"libName":"i_173","y":-47.5,"x":-260.6,"d":1,"a":1,"frameNum":1},{"frameNum":1,"x":-324.55,"d":1,"y":-45.6,"a":1},{"frameNum":58}],[{"frameNum":27},{"libName":"i_173","x":-327.55,"y":-76.5,"frameNum":1},{"libName":"i_174","x":-402.5,"y":-51.45,"frameNum":1},{"x":-86.45,"y":-49.55,"frameNum":1},{"frameNum":56}],[{"frameNum":27},{"libName":"i_173","x":-107.55,"y":-74.5,"frameNum":1},{"libName":"i_174","x":-152.5,"y":-49.45,"frameNum":1},{"x":-206.45,"y":-47.55,"frameNum":1},{"frameNum":56}],[{"frameNum":27},{"libName":"i_173","y":-73.55,"x":-213.65,"d":1,"a":1,"frameNum":1},{"libName":"i_174","y":-48.5,"x":-268.6,"d":1,"a":1,"frameNum":1},{"frameNum":1,"x":-332.55,"d":1,"y":-46.6,"a":1},{"frameNum":56}],[{"frameNum":29},{"libName":"i_174","x":-335.55,"y":-77.5,"frameNum":1},{"libName":"i_176","x":-408.5,"y":-51.45,"frameNum":1},{"x":-92.45,"y":-49.55,"frameNum":1},{"frameNum":54}],[{"frameNum":29},{"libName":"i_174","x":-115.55,"y":-75.5,"frameNum":1},{"libName":"i_176","x":-158.5,"y":-49.45,"frameNum":1},{"x":-212.45,"y":-47.55,"frameNum":1},{"frameNum":54}],[{"frameNum":29},{"libName":"i_174","y":-74.55,"x":-221.65,"d":1,"a":1,"frameNum":1},{"libName":"i_176","y":-48.5,"x":-274.6,"d":1,"a":1,"frameNum":1},{"frameNum":1,"x":-338.55,"d":1,"y":-46.6,"a":1},{"frameNum":54}],[{"frameNum":31},{"libName":"i_176","x":-341.55,"y":-77.5,"frameNum":1},{"libName":"i_173","x":-394.5,"y":-50.45,"frameNum":1},{"x":-78.45,"y":-48.55,"frameNum":1},{"frameNum":52}],[{"frameNum":31},{"libName":"i_176","x":-121.55,"y":-75.5,"frameNum":1},{"libName":"i_173","x":-144.5,"y":-48.45,"frameNum":1},{"x":-198.45,"y":-46.55,"frameNum":1},{"frameNum":52}],[{"frameNum":31},{"libName":"i_176","y":-74.55,"x":-227.65,"d":1,"a":1,"frameNum":1},{"libName":"i_173","y":-47.5,"x":-260.6,"d":1,"a":1,"frameNum":1},{"frameNum":1,"x":-324.55,"d":1,"y":-45.6,"a":1},{"frameNum":52}],[{"frameNum":33},{"libName":"i_173","x":-327.55,"y":-76.5,"frameNum":1},{"libName":"i_174","x":-402.5,"y":-51.45,"frameNum":1},{"x":-86.45,"y":-49.55,"frameNum":1},{"frameNum":50}],[{"frameNum":33},{"libName":"i_173","x":-107.55,"y":-74.5,"frameNum":1},{"libName":"i_174","x":-152.5,"y":-49.45,"frameNum":1},{"x":-206.45,"y":-47.55,"frameNum":1},{"frameNum":50}],[{"frameNum":33},{"libName":"i_173","y":-73.55,"x":-213.65,"d":1,"a":1,"frameNum":1},{"libName":"i_174","y":-48.5,"x":-268.6,"d":1,"a":1,"frameNum":1},{"frameNum":1,"x":-332.55,"d":1,"y":-46.6,"a":1},{"frameNum":50}],[{"frameNum":35},{"libName":"i_174","x":-335.55,"y":-77.5,"frameNum":1},{"libName":"i_176","x":-408.5,"y":-51.45,"frameNum":1},{"x":-92.45,"y":-49.55,"frameNum":1},{"frameNum":48}],[{"frameNum":35},{"libName":"i_174","x":-115.55,"y":-75.5,"frameNum":1},{"libName":"i_176","x":-158.5,"y":-49.45,"frameNum":1},{"x":-212.45,"y":-47.55,"frameNum":1},{"frameNum":48}],[{"frameNum":35},{"libName":"i_174","y":-74.55,"x":-221.65,"d":1,"a":1,"frameNum":1},{"libName":"i_176","y":-48.5,"x":-274.6,"d":1,"a":1,"frameNum":1},{"frameNum":1,"x":-338.55,"d":1,"y":-46.6,"a":1},{"frameNum":48}],[{"frameNum":37},{"libName":"i_176","x":-341.55,"y":-77.5,"frameNum":1},{"libName":"i_173","x":-394.5,"y":-50.45,"frameNum":1},{"x":-78.45,"y":-48.55,"frameNum":1},{"frameNum":46}],[{"frameNum":37},{"libName":"i_176","x":-121.55,"y":-75.5,"frameNum":1},{"libName":"i_173","x":-144.5,"y":-48.45,"frameNum":1},{"x":-198.45,"y":-46.55,"frameNum":1},{"frameNum":46}],[{"frameNum":37},{"libName":"i_176","y":-74.55,"x":-227.65,"d":1,"a":1,"frameNum":1},{"libName":"i_173","y":-47.5,"x":-260.6,"d":1,"a":1,"frameNum":1},{"frameNum":1,"x":-324.55,"d":1,"y":-45.6,"a":1},{"frameNum":46}],[{"frameNum":4},{"libName":"cbsmian","y":-152.2,"frameNum":33,"x":-368.7,"d":3.7661,"mcName":"cbs1atm","a":5.9106},{},{"libName":"i_173","x":-327.55,"y":-76.5,"frameNum":1},{"libName":"i_174","x":-402.5,"y":-51.45,"frameNum":1},{"x":-86.45,"y":-49.55,"frameNum":1},{"frameNum":44}],[{"frameNum":39},{"libName":"i_173","x":-107.55,"y":-74.5,"frameNum":1},{"libName":"i_174","x":-152.5,"y":-49.45,"frameNum":1},{"x":-206.45,"y":-47.55,"frameNum":1},{"frameNum":44}],[{"frameNum":39},{"libName":"i_173","y":-73.55,"x":-213.65,"d":1,"a":1,"frameNum":1},{"libName":"i_174","y":-48.5,"x":-268.6,"d":1,"a":1,"frameNum":1},{"frameNum":1,"x":-332.55,"d":1,"y":-46.6,"a":1},{"frameNum":44}],[{"frameNum":38},{"libName":"i_179","y":-149.75,"x":-71.1,"d":1.1999,"a":1.2,"frameNum":1},{},{"libName":"i_174","x":-335.55,"y":-77.5,"frameNum":1},{"libName":"i_176","x":-408.5,"y":-51.45,"frameNum":1},{"frameNum":44}],[{"frameNum":41},{"libName":"i_174","x":-115.55,"y":-75.5,"frameNum":1},{"libName":"i_176","x":-158.5,"y":-49.45,"frameNum":1},{"frameNum":44}],[{"frameNum":41},{"libName":"i_174","y":-74.55,"x":-221.65,"d":1,"a":1,"frameNum":1},{"libName":"i_176","y":-48.5,"x":-274.6,"d":1,"a":1,"frameNum":1},{"frameNum":44}],[{"frameNum":40},{"libName":"i_179","y":-168.55,"x":-193.4,"d":1.3,"a":1.3,"frameNum":1},{},{"libName":"i_176","x":-341.55,"y":-77.5,"frameNum":1},{"frameNum":44}],[{"frameNum":40},{"libName":"i_180","y":-161.75,"x":-69.9,"d":1.1999,"a":1.2,"frameNum":1},{},{"libName":"i_176","x":-121.55,"y":-75.5,"frameNum":1},{"frameNum":44}],[{"frameNum":43},{"libName":"i_176","y":-74.55,"x":-227.65,"d":1,"a":1,"frameNum":1},{"frameNum":44}],[{"frameNum":42},{"libName":"i_179","y":-138.95,"x":-286.8,"d":1.1,"a":1.1,"frameNum":1},{"frameNum":1,"x":-372.2,"d":0.9,"y":-109.35,"a":0.9},{"frameNum":43}],[{"frameNum":42},{"libName":"i_180","y":-181.55,"x":-192.1,"d":1.3,"a":1.3,"frameNum":1},{"frameNum":1,"x":-285.7,"d":1.1,"y":-149.95,"a":1.1},{"frameNum":43}],[{"frameNum":42},{"libName":"i_181","y":-164.15,"x":-81.9,"d":1.1999,"a":1.2,"frameNum":1},{"frameNum":1,"x":-205.1,"d":1.3,"y":-184.15,"a":1.3},{"frameNum":43}],[{"frameNum":44},{"libName":"i_182","y":-188.15,"x":-84.3,"d":1.1999,"a":1.2,"frameNum":1},{"frameNum":43}],[{"frameNum":38},{"libName":"cbsmian","y":-152.2,"frameNum":1,"x":-61.1,"d":3.7661,"mcName":"cbsatm","a":2.0955},{"x":-197.05,"y":-152.2,"a":4.4006,"d":3.7661,"mcName":"cbsatm","frameNum":1},{"x":-277.05,"y":-152.2,"a":4.4006,"d":3.7661,"mcName":"cbsatm","frameNum":1},{"x":-357.05,"y":-152.2,"a":4.4006,"d":3.7661,"mcName":"cbsatm","frameNum":1},{"frameNum":43}]],"screenH":640,"totalFrame":91}}}