{"file":"hero_ichigo01.png","frames":{"i_549":{"x":737,"h":282,"w":263,"y":185},"i_576":{"x":737,"h":364,"w":406,"y":479},"i_606":{"x":1357,"h":244,"w":243,"y":0},"i_122":{"x":1047,"h":183,"w":308,"y":0},"i_515":{"x":737,"h":183,"w":308,"y":0},"i_575":{"x":0,"h":280,"w":374,"y":777},"i_614":{"x":376,"h":558,"w":578,"y":845},"i_601":{"x":0,"h":321,"w":321,"y":454},"i_573":{"x":1602,"h":222,"w":280,"y":0},"i_602":{"x":1295,"h":296,"w":295,"y":469},"i_620":{"x":1182,"h":573,"w":591,"y":1405},"i_622":{"x":0,"h":561,"w":588,"y":1405},"i_621":{"x":590,"h":565,"w":590,"y":1405},"i_596":{"x":456,"h":280,"w":279,"y":246},"i_604":{"x":1602,"h":260,"w":259,"y":224},"i_577":{"x":1145,"h":370,"w":426,"y":767},"i_547":{"x":310,"h":214,"w":194,"y":0},"i_605":{"x":219,"h":236,"w":235,"y":216},"i_597":{"x":1002,"h":292,"w":291,"y":185},"i_607":{"x":0,"h":218,"w":217,"y":102},"i_458":{"x":0,"h":100,"w":308,"y":0},"i_548":{"x":506,"h":240,"w":229,"y":0},"i_599":{"x":1592,"h":312,"w":311,"y":486}}}
