{"fileName":"assist_kon","version":1597298446927,"stageHgith":1,"sArr":["l_47","l_22"],"imgScale":{},"inputScale":1,"scale":1,"clipping":{"clippingPadding":3},"mcObjs":{"root":{"direction":1,"screenH":640,"totalFrame":102,"layers":[[{},{"libName":"i_1","x":-9.85,"frameNum":1,"y":-30.85},{"libName":"i_2","x":-8.85,"frameNum":1,"y":-30.85},{"libName":"i_3","x":-8.85,"frameNum":1,"y":-30.85},{"libName":"i_4","x":-8.85,"frameNum":1,"y":-30.85},{"libName":"i_1","x":-9.85,"frameNum":1,"y":-30.85},{"libName":"i_2","x":-8.85,"frameNum":1,"y":-30.85},{"libName":"i_1","x":-9.85,"frameNum":16,"y":-30.85},{"libName":"i_5","x":-13,"frameNum":1,"y":-26},{"libName":"i_6","x":-15,"frameNum":1,"y":-31},{"libName":"i_7","x":-11,"frameNum":1,"y":-32},{"libName":"i_8","x":-7,"frameNum":1,"y":-50},{"libName":"i_10","x":-7,"frameNum":1,"y":-56},{"libName":"i_11","x":-7,"frameNum":1,"y":-59},{"libName":"i_12","x":-7,"frameNum":1,"y":-65},{"libName":"i_13","x":-7,"frameNum":1,"y":-69},{"libName":"i_14","x":-7,"frameNum":1,"y":-66},{"libName":"i_15","x":-7,"frameNum":1,"y":-61},{"libName":"i_16","x":-7,"frameNum":1,"y":-57},{"libName":"i_17","x":-9,"frameNum":1,"y":-51},{"libName":"i_18","x":-9,"frameNum":1,"y":-48},{"libName":"i_19","x":-9,"frameNum":1,"y":-43},{"libName":"i_20","x":-9,"frameNum":1,"y":-40},{"libName":"i_21","x":-10,"frameNum":1,"y":-34},{"libName":"i_22","x":-9,"frameNum":1,"y":-31},{"libName":"i_3","x":-9,"frameNum":1,"y":-31},{"libName":"i_4","x":-9,"frameNum":1,"y":-31},{"libName":"i_1","x":-9.85,"frameNum":1,"y":-30.85},{"libName":"i_2","x":-8.85,"frameNum":1,"y":-30.85},{"libName":"i_3","x":-8.85,"frameNum":1,"y":-30.85},{"libName":"i_4","x":-8.85,"frameNum":1,"y":-30.85},{"libName":"i_1","x":-9.85,"frameNum":1,"y":-30.85},{"libName":"i_2","x":-8.85,"frameNum":1,"y":-30.85},{"libName":"i_3","x":-8.85,"frameNum":1,"y":-30.85},{"libName":"i_4","x":-8.85,"frameNum":1,"y":-30.85},{"libName":"i_1","x":-9.85,"frameNum":1,"y":-30.85},{"libName":"i_2","x":-8.85,"frameNum":1,"y":-30.85},{"libName":"i_3","x":-8.85,"frameNum":1,"y":-30.85},{"libName":"i_4","x":-8.85,"frameNum":1,"y":-30.85},{"libName":"i_1","x":-9.85,"frameNum":1,"y":-30.85},{"libName":"i_2","x":-8.85,"frameNum":1,"y":-30.85},{"libName":"i_3","x":-8.85,"frameNum":1,"y":-30.85},{"libName":"i_4","x":-8.85,"frameNum":1,"y":-30.85},{"libName":"i_1","x":-9.85,"y":-30.85},{}],[{"frameNum":35},{"x":10.95,"frameNum":1,"y":-54.35,"libName":"atm1","mcName":"atm1","d":0.8225,"a":0.5678},{"x":18.95,"frameNum":1,"y":-57.85,"mcName":"atm1","d":0.8225,"a":0.5678},{"x":24.45,"frameNum":1,"y":-61.35,"mcName":"atm1","d":0.8225,"a":0.5678},{"x":29.95,"frameNum":1,"y":-66.35,"mcName":"atm1","d":0.8225,"a":0.5678},{"x":33.45,"frameNum":1,"y":-71.35,"mcName":"atm1","d":0.8225,"a":0.5678},{"x":38.95,"frameNum":1,"y":-67.35,"mcName":"atm1","d":0.8225,"a":0.5678},{"x":45.95,"frameNum":1,"y":-62.35,"mcName":"atm1","d":0.8225,"a":0.5678},{"x":50.95,"frameNum":1,"y":-58.35,"mcName":"atm1","d":0.8225,"a":0.5678},{"x":55.95,"frameNum":1,"y":-53.35,"mcName":"atm1","d":0.8225,"a":0.5678},{"x":59.95,"frameNum":1,"y":-49.85,"mcName":"atm1","d":0.8225,"a":0.5678},{"x":65.95,"frameNum":1,"y":-44.85,"mcName":"atm1","d":0.8225,"a":0.5678},{"x":72.95,"frameNum":1,"y":-41.85,"mcName":"atm1","d":0.8225,"a":0.5678},{"x":74.45,"frameNum":1,"y":-36.35,"mcName":"atm1","d":0.8225,"a":0.5678},{"x":80.45,"frameNum":1,"y":-31.35,"mcName":"atm1","d":0.8225,"a":0.5678},{"frameNum":37}]],"stageHeight":1,"frameTime":33,"soundObj":{"36":[{"libName":"l_22"}],"61":[{"libName":"l_47"}]}},"atm1":{"direction":1,"screenH":640,"totalFrame":1,"stageHeight":41.5,"frameTime":33,"layers":[[{"libName":"i_9","x":0,"y":0}],[{}]],"frameLabels":{"pai":{"begin":0}}}},"imgArr":[{"size":5014,"name":"0"}],"stageWidth":1,"imgP":{"i_3":{},"i_18":{},"i_11":{},"i_20":{},"i_2":{},"i_1":{},"i_16":{},"i_15":{},"i_21":{},"i_14":{},"i_17":{},"i_7":{},"i_8":{},"i_4":{},"i_5":{},"i_10":{},"i_13":{},"i_6":{},"i_22":{},"i_19":{},"i_12":{}}}