{"file":"hero_geliou01.png","frames":{"i_193":{"h":511,"y":1074,"x":0,"w":630},"i_195":{"h":511,"y":453,"x":1368,"w":630},"i_142":{"h":179,"y":0,"x":368,"w":366},"i_147":{"h":199,"y":360,"x":0,"w":366},"i_192":{"h":511,"y":966,"x":632,"w":630},"i_145":{"h":189,"y":181,"x":368,"w":366},"i_143":{"h":181,"y":177,"x":0,"w":366},"i_197":{"h":511,"y":453,"x":736,"w":630},"i_194":{"h":511,"y":561,"x":0,"w":630},"i_196":{"h":511,"y":1479,"x":1264,"w":631},"i_144":{"h":185,"y":0,"x":736,"w":366},"i_190":{"h":511,"y":966,"x":1264,"w":630},"i_146":{"h":197,"y":0,"x":1104,"w":367},"i_191":{"h":511,"y":1479,"x":632,"w":630},"i_141":{"h":175,"y":0,"x":0,"w":366},"i_201":{"h":252,"y":199,"x":736,"w":1010}}}
